{
  "centroid_coordinates": [],
  "features": [
    {
      "geometry": {
        "coordinates": [
          [
            [
              [
                -74.914797,
                40.08828
              ],
              [
                -74.914953,
                40.088604
              ],
              [
                -74.914581,
                40.090283
              ],
              [
                -74.913828,
                40.092551
              ],
              [
                -74.873417,
                40.098233
              ],
              [
                -74.873866,
                40.098529
              ],
              [
                -74.866075,
                40.100938
              ],
              [
                -74.868805,
                40.097847
              ],
              [
                -74.869861,
                40.09714
              ],
              [
                -74.869829,
                40.096749
              ],
              [
                -74.869399,
                40.096211
              ],
              [
                -74.868591,
                40.095689
              ],
              [
                -74.866659,
                40.09502
              ],
              [
                -74.86402,
                40.095164
              ],
              [
                -74.863663,
                40.095049
              ],
              [
                -74.862582,
                40.093973
              ],
              [
                -74.859292,
                40.093085
              ],
              [
                -74.856619,
                40.091313
              ],
              [
                -74.858005,
                40.089602
              ],
              [
                -74.858987,
                40.086757
              ],
              [
                -74.859721,
                40.085311
              ],
              [
                -74.861756,
                40.083462
              ],
              [
                -74.863422,
                40.082635
              ],
              [
                -74.865489,
                40.082133
              ],
              [
                -74.872258,
                40.081163
              ],
              [
                -74.877533,
                40.079957
              ],
              [
                -74.879916,
                40.079221
              ],
              [
                -74.885978,
                40.07697
              ],
              [
                -74.889685,
                40.075834
              ],
              [
                -74.90009,
                40.07296
              ],
              [
                -74.905815,
                40.071159
              ],
              [
                -74.909103,
                40.070505
              ],
              [
                -74.908831,
                40.076999
              ],
              [
                -74.90967,
                40.082679
              ],
              [
                -74.910715,
                40.084509
              ],
              [
                -74.913444,
                40.085804
              ],
              [
                -74.914689,
                40.087734
              ],
              [
                -74.914797,
                40.08828
              ]
            ]
          ]
        ],
        "type": "MultiPolygon"
      },
      "industries": {
        "allOther": 0,
        "goodsProducing": 0,
        "tradeTransUtil": 1
      },
      "type": "Feature",
      "workTract": "42017100302"
    },
    {
      "geometry": {
        "coordinates": [
          [
            [
              [
                -75.637568,
                39.983514
              ],
              [
                -75.639743,
                39.986432
              ],
              [
                -75.638581,
                39.987431
              ],
              [
                -75.633709,
                39.987799
              ],
              [
                -75.631673,
                39.988203
              ],
              [
                -75.628609,
                39.988236
              ],
              [
                -75.626288,
                39.988746
              ],
              [
                -75.623681,
                39.98886
              ],
              [
                -75.620195,
                39.989763
              ],
              [
                -75.617097,
                39.991078
              ],
              [
                -75.614281,
                39.991756
              ],
              [
                -75.613262,
                39.991827
              ],
              [
                -75.608946,
                39.993187
              ],
              [
                -75.606161,
                39.992919
              ],
              [
                -75.59717,
                39.996434
              ],
              [
                -75.596031,
                39.996379
              ],
              [
                -75.594608,
                39.99559
              ],
              [
                -75.593456,
                39.99711
              ],
              [
                -75.59312,
                39.998144
              ],
              [
                -75.583907,
                40.002001
              ],
              [
                -75.579782,
                39.996364
              ],
              [
                -75.572251,
                39.986714
              ],
              [
                -75.571388,
                39.985929
              ],
              [
                -75.570435,
                39.984366
              ],
              [
                -75.568306,
                39.98162
              ],
              [
                -75.575195,
                39.978291
              ],
              [
                -75.578894,
                39.980302
              ],
              [
                -75.582505,
                39.979588
              ],
              [
                -75.584586,
                39.978351
              ],
              [
                -75.586641,
                39.977408
              ],
              [
                -75.588126,
                39.979454
              ],
              [
                -75.590914,
                39.979314
              ],
              [
                -75.594018,
                39.977995
              ],
              [
                -75.595435,
                39.976948
              ],
              [
                -75.598543,
                39.975223
              ],
              [
                -75.60513,
                39.973736
              ],
              [
                -75.610293,
                39.970901
              ],
              [
                -75.62312,
                39.965173
              ],
              [
                -75.633515,
                39.978078
              ],
              [
                -75.637568,
                39.983514
              ]
            ]
          ]
        ],
        "type": "MultiPolygon"
      },
      "industries": {
        "allOther": 0,
        "goodsProducing": 0,
        "tradeTransUtil": 1
      },
      "type": "Feature",
      "workTract": "42029302703"
    },
    {
      "geometry": {
        "coordinates": [
          [
            [
              [
                -75.581155,
                39.840428
              ],
              [
                -75.579926,
                39.838862
              ],
              [
                -75.593099,
                39.837723
              ],
              [
                -75.59211,
                39.838768
              ],
              [
                -75.591291,
                39.840445
              ],
              [
                -75.589818,
                39.8426
              ],
              [
                -75.588741,
                39.843507
              ],
              [
                -75.58713,
                39.844303
              ],
              [
                -75.586339,
                39.844315
              ],
              [
                -75.583825,
                39.843022
              ],
              [
                -75.582029,
                39.841453
              ],
              [
                -75.581155,
                39.840428
              ]
            ]
          ],
          [
            [
              [
                -75.579966,
                39.88397
              ],
              [
                -75.580414,
                39.883746
              ],
              [
                -75.582416,
                39.885741
              ],
              [
                -75.584186,
                39.884573
              ],
              [
                -75.58449,
                39.885009
              ],
              [
                -75.585059,
                39.884871
              ],
              [
                -75.585352,
                39.884591
              ],
              [
                -75.585684,
                39.884778
              ],
              [
                -75.586249,
                39.884814
              ],
              [
                -75.587192,
                39.884207
              ],
              [
                -75.584761,
                39.880978
              ],
              [
                -75.597914,
                39.874464
              ],
              [
                -75.598228,
                39.874815
              ],
              [
                -75.598514,
                39.87554
              ],
              [
                -75.598431,
                39.876633
              ],
              [
                -75.598733,
                39.877053
              ],
              [
                -75.599785,
                39.877573
              ],
              [
                -75.600695,
                39.877718
              ],
              [
                -75.601548,
                39.87811
              ],
              [
                -75.602019,
                39.879557
              ],
              [
                -75.602799,
                39.880436
              ],
              [
                -75.607269,
                39.883215
              ],
              [
                -75.609931,
                39.884561
              ],
              [
                -75.610044,
                39.884867
              ],
              [
                -75.609663,
                39.885441
              ],
              [
                -75.60963,
                39.885945
              ],
              [
                -75.609805,
                39.886315
              ],
              [
                -75.610378,
                39.886849
              ],
              [
                -75.611632,
                39.887196
              ],
              [
                -75.612372,
                39.887599
              ],
              [
                -75.614419,
                39.889319
              ],
              [
                -75.616119,
                39.890012
              ],
              [
                -75.617214,
                39.890718
              ],
              [
                -75.617272,
                39.891165
              ],
              [
                -75.61579,
                39.892842
              ],
              [
                -75.61576,
                39.893189
              ],
              [
                -75.616037,
                39.893513
              ],
              [
                -75.62044,
                39.895525
              ],
              [
                -75.620719,
                39.89579
              ],
              [
                -75.621747,
                39.896053
              ],
              [
                -75.622223,
                39.896414
              ],
              [
                -75.623168,
                39.897604
              ],
              [
                -75.623801,
                39.898709
              ],
              [
                -75.6239,
                39.899462
              ],
              [
                -75.623275,
                39.902522
              ],
              [
                -75.623279,
                39.904166
              ],
              [
                -75.625157,
                39.906057
              ],
              [
                -75.626644,
                39.909253
              ],
              [
                -75.626529,
                39.910314
              ],
              [
                -75.62572,
                39.912043
              ],
              [
                -75.626002,
                39.912641
              ],
              [
                -75.628767,
                39.913659
              ],
              [
                -75.632027,
                39.914459
              ],
              [
                -75.63323,
                39.914509
              ],
              [
                -75.633391,
                39.914918
              ],
              [
                -75.614641,
                39.92372
              ],
              [
                -75.610783,
                39.928709
              ],
              [
                -75.607459,
                39.924354
              ],
              [
                -75.60071,
                39.916114
              ],
              [
                -75.596808,
                39.91082
              ],
              [
                -75.594524,
                39.91188
              ],
              [
                -75.587905,
                39.903643
              ],
              [
                -75.570336,
                39.911766
              ],
              [
                -75.562539,
                39.901638
              ],
              [
                -75.573381,
                39.896397
              ],
              [
                -75.572419,
                39.89474
              ],
              [
                -75.572292,
                39.893194
              ],
              [
                -75.573655,
                39.892346
              ],
              [
                -75.574253,
                39.892153
              ],
              [
                -75.571162,
                39.888136
              ],
              [
                -75.579966,
                39.88397
              ]
            ]
          ]
        ],
        "type": "MultiPolygon"
      },
      "industries": {
        "allOther": 1,
        "goodsProducing": 0,
        "tradeTransUtil": 0
      },
      "type": "Feature",
      "workTract": "42029303100"
    },
    {
      "geometry": {
        "coordinates": [
          [
            [
              [
                -75.57125,
                39.770757
              ],
              [
                -75.57081,
                39.770962
              ],
              [
                -75.569584,
                39.770968
              ],
              [
                -75.56777,
                39.770436
              ],
              [
                -75.565191,
                39.769232
              ],
              [
                -75.56373,
                39.768969
              ],
              [
                -75.56046,
                39.768895
              ],
              [
                -75.559114,
                39.768496
              ],
              [
                -75.55835,
                39.767822
              ],
              [
                -75.556641,
                39.765625
              ],
              [
                -75.556633,
                39.765221
              ],
              [
                -75.556808,
                39.765083
              ],
              [
                -75.55732,
                39.7631
              ],
              [
                -75.557312,
                39.762062
              ],
              [
                -75.556869,
                39.760601
              ],
              [
                -75.557669,
                39.760395
              ],
              [
                -75.558095,
                39.761338
              ],
              [
                -75.558336,
                39.761556
              ],
              [
                -75.559616,
                39.762007
              ],
              [
                -75.560491,
                39.762525
              ],
              [
                -75.561942,
                39.762742
              ],
              [
                -75.565315,
                39.760563
              ],
              [
                -75.568161,
                39.756316
              ],
              [
                -75.567856,
                39.756016
              ],
              [
                -75.568626,
                39.755634
              ],
              [
                -75.57013,
                39.753526
              ],
              [
                -75.573635,
                39.754965
              ],
              [
                -75.574977,
                39.752919
              ],
              [
                -75.578608,
                39.754406
              ],
              [
                -75.575294,
                39.759303
              ],
              [
                -75.580483,
                39.762749
              ],
              [
                -75.579778,
                39.763546
              ],
              [
                -75.576797,
                39.768028
              ],
              [
                -75.576436,
                39.769193
              ],
              [
                -75.575638,
                39.768911
              ],
              [
                -75.574705,
                39.76896
              ],
              [
                -75.57125,
                39.770757
              ]
            ]
          ]
        ],
        "type": "MultiPolygon"
      },
      "industries": {
        "allOther": 0,
        "goodsProducing": 1,
        "tradeTransUtil": 0
      },
      "type": "Feature",
      "workTract": "10003001300"
    },
    {
      "geometry": {
        "coordinates": [
          [
            [
              [
                -75.752727,
                39.698271
              ],
              [
                -75.752441,
                39.699318
              ],
              [
                -75.752724,
                39.700078
              ],
              [
                -75.75251,
                39.701664
              ],
              [
                -75.752792,
                39.702034
              ],
              [
                -75.754265,
                39.702679
              ],
              [
                -75.75547,
                39.70443
              ],
              [
                -75.756897,
                39.705383
              ],
              [
                -75.758568,
                39.707901
              ],
              [
                -75.759506,
                39.708752
              ],
              [
                -75.759666,
                39.70916
              ],
              [
                -75.759743,
                39.71109
              ],
              [
                -75.759285,
                39.713657
              ],
              [
                -75.758814,
                39.714909
              ],
              [
                -75.758083,
                39.715619
              ],
              [
                -75.758037,
                39.716093
              ],
              [
                -75.758395,
                39.716529
              ],
              [
                -75.759521,
                39.71711
              ],
              [
                -75.759973,
                39.717839
              ],
              [
                -75.760592,
                39.717992
              ],
              [
                -75.761861,
                39.719091
              ],
              [
                -75.764156,
                39.720182
              ],
              [
                -75.764844,
                39.721995
              ],
              [
                -75.765281,
                39.724296
              ],
              [
                -75.765965,
                39.724756
              ],
              [
                -75.766862,
                39.724878
              ],
              [
                -75.767212,
                39.725291
              ],
              [
                -75.767084,
                39.726437
              ],
              [
                -75.766594,
                39.727231
              ],
              [
                -75.765653,
                39.727731
              ],
              [
                -75.765201,
                39.728494
              ],
              [
                -75.764947,
                39.728654
              ],
              [
                -75.764513,
                39.728726
              ],
              [
                -75.763589,
                39.728485
              ],
              [
                -75.763142,
                39.728567
              ],
              [
                -75.763017,
                39.728825
              ],
              [
                -75.763116,
                39.729664
              ],
              [
                -75.7629,
                39.729833
              ],
              [
                -75.762224,
                39.729976
              ],
              [
                -75.761232,
                39.72937
              ],
              [
                -75.760595,
                39.729562
              ],
              [
                -75.760352,
                39.730205
              ],
              [
                -75.760381,
                39.731687
              ],
              [
                -75.759728,
                39.73281
              ],
              [
                -75.757196,
                39.732762
              ],
              [
                -75.75537,
                39.729012
              ],
              [
                -75.753553,
                39.72977
              ],
              [
                -75.749975,
                39.730753
              ],
              [
                -75.74906,
                39.731485
              ],
              [
                -75.742704,
                39.733502
              ],
              [
                -75.741365,
                39.733448
              ],
              [
                -75.738574,
                39.732647
              ],
              [
                -75.735391,
                39.732866
              ],
              [
                -75.730315,
                39.736889
              ],
              [
                -75.72674,
                39.740411
              ],
              [
                -75.724762,
                39.739366
              ],
              [
                -75.722318,
                39.73836
              ],
              [
                -75.720404,
                39.73728
              ],
              [
                -75.71738,
                39.734339
              ],
              [
                -75.715428,
                39.732937
              ],
              [
                -75.712749,
                39.72824
              ],
              [
                -75.711552,
                39.719464
              ],
              [
                -75.716,
                39.720259
              ],
              [
                -75.717626,
                39.720095
              ],
              [
                -75.717102,
                39.719589
              ],
              [
                -75.716938,
                39.718842
              ],
              [
                -75.717975,
                39.71709
              ],
              [
                -75.718259,
                39.716079
              ],
              [
                -75.718792,
                39.71553
              ],
              [
                -75.718899,
                39.714997
              ],
              [
                -75.718642,
                39.714052
              ],
              [
                -75.717838,
                39.713509
              ],
              [
                -75.71786,
                39.713201
              ],
              [
                -75.7183,
                39.712668
              ],
              [
                -75.719303,
                39.712206
              ],
              [
                -75.720071,
                39.712091
              ],
              [
                -75.720632,
                39.711509
              ],
              [
                -75.721301,
                39.71119
              ],
              [
                -75.721364,
                39.710789
              ],
              [
                -75.722381,
                39.709718
              ],
              [
                -75.722366,
                39.708833
              ],
              [
                -75.720424,
                39.708098
              ],
              [
                -75.720352,
                39.706291
              ],
              [
                -75.719826,
                39.705665
              ],
              [
                -75.720096,
                39.705006
              ],
              [
                -75.72048,
                39.705127
              ],
              [
                -75.720558,
                39.705006
              ],
              [
                -75.720501,
                39.7045
              ],
              [
                -75.719946,
                39.703968
              ],
              [
                -75.719789,
                39.703594
              ],
              [
                -75.719454,
                39.700859
              ],
              [
                -75.719567,
                39.699914
              ],
              [
                -75.719318,
                39.698673
              ],
              [
                -75.719929,
                39.698052
              ],
              [
                -75.719999,
                39.697025
              ],
              [
                -75.71958,
                39.696152
              ],
              [
                -75.719864,
                39.695581
              ],
              [
                -75.720404,
                39.695279
              ],
              [
                -75.720381,
                39.694309
              ],
              [
                -75.722205,
                39.69354
              ],
              [
                -75.724163,
                39.692463
              ],
              [
                -75.725127,
                39.692294
              ],
              [
                -75.726063,
                39.692497
              ],
              [
                -75.726858,
                39.692871
              ],
              [
                -75.727954,
                39.692911
              ],
              [
                -75.732501,
                39.692289
              ],
              [
                -75.734524,
                39.692364
              ],
              [
                -75.734648,
                39.692187
              ],
              [
                -75.734626,
                39.691231
              ],
              [
                -75.734445,
                39.689709
              ],
              [
                -75.734669,
                39.689386
              ],
              [
                -75.734934,
                39.689335
              ],
              [
                -75.736834,
                39.689802
              ],
              [
                -75.741716,
                39.690268
              ],
              [
                -75.745883,
                39.689671
              ],
              [
                -75.747939,
                39.689638
              ],
              [
                -75.74959,
                39.689166
              ],
              [
                -75.751395,
                39.689634
              ],
              [
                -75.75308,
                39.689794
              ],
              [
                -75.753804,
                39.690827
              ],
              [
                -75.755596,
                39.692442
              ],
              [
                -75.755693,
                39.692769
              ],
              [
                -75.755535,
                39.693377
              ],
              [
                -75.75486,
                39.694221
              ],
              [
                -75.753182,
                39.697122
              ],
              [
                -75.752727,
                39.698271
              ]
            ]
          ]
        ],
        "type": "MultiPolygon"
      },
      "industries": {
        "allOther": 1,
        "goodsProducing": 0,
        "tradeTransUtil": 0
      },
      "type": "Feature",
      "workTract": "10003013610"
    },
    {
      "geometry": {
        "coordinates": [
          [
            [
              [
                -75.694762,
                39.618795
              ],
              [
                -75.696101,
                39.618148
              ],
              [
                -75.698847,
                39.616323
              ],
              [
                -75.704047,
                39.6118
              ],
              [
                -75.705006,
                39.611122
              ],
              [
                -75.706934,
                39.610229
              ],
              [
                -75.711255,
                39.608711
              ],
              [
                -75.745224,
                39.605615
              ],
              [
                -75.746249,
                39.608594
              ],
              [
                -75.746251,
                39.610283
              ],
              [
                -75.746128,
                39.611142
              ],
              [
                -75.745736,
                39.611993
              ],
              [
                -75.745651,
                39.613375
              ],
              [
                -75.744435,
                39.621444
              ],
              [
                -75.743442,
                39.639389
              ],
              [
                -75.743544,
                39.641109
              ],
              [
                -75.743888,
                39.642632
              ],
              [
                -75.74549,
                39.6458
              ],
              [
                -75.746144,
                39.646785
              ],
              [
                -75.745898,
                39.646787
              ],
              [
                -75.745977,
                39.646706
              ],
              [
                -75.743885,
                39.643287
              ],
              [
                -75.74449,
                39.646042
              ],
              [
                -75.743913,
                39.646516
              ],
              [
                -75.742322,
                39.646663
              ],
              [
                -75.742192,
                39.64616
              ],
              [
                -75.742304,
                39.645762
              ],
              [
                -75.742567,
                39.645525
              ],
              [
                -75.742307,
                39.644636
              ],
              [
                -75.740995,
                39.643343
              ],
              [
                -75.739821,
                39.64289
              ],
              [
                -75.738413,
                39.642807
              ],
              [
                -75.738035,
                39.642664
              ],
              [
                -75.737623,
                39.642095
              ],
              [
                -75.736555,
                39.642093
              ],
              [
                -75.735279,
                39.641193
              ],
              [
                -75.733451,
                39.641435
              ],
              [
                -75.732798,
                39.641256
              ],
              [
                -75.731515,
                39.639499
              ],
              [
                -75.731295,
                39.638653
              ],
              [
                -75.729652,
                39.638153
              ],
              [
                -75.729393,
                39.637897
              ],
              [
                -75.728004,
                39.637272
              ],
              [
                -75.727737,
                39.636345
              ],
              [
                -75.727554,
                39.636223
              ],
              [
                -75.726616,
                39.636154
              ],
              [
                -75.725792,
                39.63586
              ],
              [
                -75.72522,
                39.636032
              ],
              [
                -75.724678,
                39.636696
              ],
              [
                -75.723816,
                39.637299
              ],
              [
                -75.723503,
                39.637856
              ],
              [
                -75.723549,
                39.638363
              ],
              [
                -75.722771,
                39.639099
              ],
              [
                -75.722183,
                39.638939
              ],
              [
                -75.720662,
                39.637886
              ],
              [
                -75.720558,
                39.636845
              ],
              [
                -75.720329,
                39.636318
              ],
              [
                -75.719887,
                39.636024
              ],
              [
                -75.719315,
                39.636169
              ],
              [
                -75.718831,
                39.636559
              ],
              [
                -75.718163,
                39.637569
              ],
              [
                -75.717597,
                39.638006
              ],
              [
                -75.717007,
                39.638948
              ],
              [
                -75.71604,
                39.639359
              ],
              [
                -75.715559,
                39.639762
              ],
              [
                -75.715386,
                39.639788
              ],
              [
                -75.714741,
                39.639354
              ],
              [
                -75.714323,
                39.639445
              ],
              [
                -75.712979,
                39.639072
              ],
              [
                -75.712472,
                39.639291
              ],
              [
                -75.711945,
                39.639206
              ],
              [
                -75.710886,
                39.640165
              ],
              [
                -75.711466,
                39.641433
              ],
              [
                -75.71157,
                39.642773
              ],
              [
                -75.711145,
                39.643024
              ],
              [
                -75.71069,
                39.64274
              ],
              [
                -75.710263,
                39.642692
              ],
              [
                -75.709419,
                39.643028
              ],
              [
                -75.709049,
                39.643024
              ],
              [
                -75.708846,
                39.642671
              ],
              [
                -75.708034,
                39.642152
              ],
              [
                -75.708506,
                39.641549
              ],
              [
                -75.707268,
                39.640194
              ],
              [
                -75.707195,
                39.639872
              ],
              [
                -75.707537,
                39.639246
              ],
              [
                -75.708357,
                39.638672
              ],
              [
                -75.709209,
                39.637243
              ],
              [
                -75.708608,
                39.636384
              ],
              [
                -75.70778,
                39.636251
              ],
              [
                -75.706451,
                39.635743
              ],
              [
                -75.705965,
                39.635854
              ],
              [
                -75.70552,
                39.635542
              ],
              [
                -75.706112,
                39.63359
              ],
              [
                -75.706112,
                39.632701
              ],
              [
                -75.704363,
                39.626178
              ],
              [
                -75.703767,
                39.625578
              ],
              [
                -75.701433,
                39.6245
              ],
              [
                -75.696431,
                39.620022
              ],
              [
                -75.694762,
                39.618795
              ]
            ]
          ]
        ],
        "type": "MultiPolygon"
      },
      "industries": {
        "allOther": 0,
        "goodsProducing": 2,
        "tradeTransUtil": 0
      },
      "type": "Feature",
      "workTract": "10003014808"
    },
    {
      "geometry": {
        "coordinates": [
          [
            [
              [
                -75.884846,
                39.518904
              ],
              [
                -75.883314,
                39.523542
              ],
              [
                -75.882225,
                39.526239
              ],
              [
                -75.880143,
                39.52983
              ],
              [
                -75.879469,
                39.531457
              ],
              [
                -75.877532,
                39.534976
              ],
              [
                -75.876811,
                39.53669
              ],
              [
                -75.874662,
                39.539204
              ],
              [
                -75.87129,
                39.541129
              ],
              [
                -75.868433,
                39.542993
              ],
              [
                -75.865059,
                39.54595
              ],
              [
                -75.863994,
                39.547242
              ],
              [
                -75.861237,
                39.552943
              ],
              [
                -75.859836,
                39.554819
              ],
              [
                -75.855177,
                39.559125
              ],
              [
                -75.853575,
                39.561599
              ],
              [
                -75.853106,
                39.562612
              ],
              [
                -75.850749,
                39.562611
              ],
              [
                -75.848743,
                39.5652
              ],
              [
                -75.848885,
                39.565496
              ],
              [
                -75.848301,
                39.566735
              ],
              [
                -75.83582,
                39.569343
              ],
              [
                -75.834764,
                39.569087
              ],
              [
                -75.831148,
                39.566991
              ],
              [
                -75.829212,
                39.566559
              ],
              [
                -75.828396,
                39.566642
              ],
              [
                -75.82685,
                39.567494
              ],
              [
                -75.826633,
                39.567946
              ],
              [
                -75.82677,
                39.569509
              ],
              [
                -75.826644,
                39.569644
              ],
              [
                -75.823646,
                39.569836
              ],
              [
                -75.822755,
                39.571249
              ],
              [
                -75.822146,
                39.57148
              ],
              [
                -75.821345,
                39.571141
              ],
              [
                -75.820384,
                39.570177
              ],
              [
                -75.819116,
                39.570533
              ],
              [
                -75.818187,
                39.571025
              ],
              [
                -75.817564,
                39.571023
              ],
              [
                -75.817315,
                39.570807
              ],
              [
                -75.817427,
                39.570431
              ],
              [
                -75.817285,
                39.570229
              ],
              [
                -75.815971,
                39.569743
              ],
              [
                -75.815129,
                39.570133
              ],
              [
                -75.814229,
                39.571038
              ],
              [
                -75.810849,
                39.565879
              ],
              [
                -75.810714,
                39.565867
              ],
              [
                -75.805572,
                39.566831
              ],
              [
                -75.792893,
                39.569834
              ],
              [
                -75.784807,
                39.571325
              ],
              [
                -75.782356,
                39.572296
              ],
              [
                -75.772073,
                39.445333
              ],
              [
                -75.772655,
                39.445568
              ],
              [
                -75.773918,
                39.44563
              ],
              [
                -75.776021,
                39.446228
              ],
              [
                -75.776241,
                39.445323
              ],
              [
                -75.775727,
                39.443693
              ],
              [
                -75.775736,
                39.442152
              ],
              [
                -75.778716,
                39.439293
              ],
              [
                -75.77975,
                39.438698
              ],
              [
                -75.781994,
                39.437967
              ],
              [
                -75.78282,
                39.437967
              ],
              [
                -75.786303,
                39.438587
              ],
              [
                -75.787365,
                39.43861
              ],
              [
                -75.788861,
                39.438338
              ],
              [
                -75.7889,
                39.43883
              ],
              [
                -75.788699,
                39.439486
              ],
              [
                -75.789008,
                39.439943
              ],
              [
                -75.791569,
                39.44048
              ],
              [
                -75.792882,
                39.440428
              ],
              [
                -75.793273,
                39.440803
              ],
              [
                -75.794104,
                39.440678
              ],
              [
                -75.795292,
                39.4409
              ],
              [
                -75.797051,
                39.440673
              ],
              [
                -75.801328,
                39.441472
              ],
              [
                -75.805909,
                39.441667
              ],
              [
                -75.807379,
                39.441997
              ],
              [
                -75.808331,
                39.441992
              ],
              [
                -75.809806,
                39.442259
              ],
              [
                -75.811681,
                39.442362
              ],
              [
                -75.812642,
                39.442127
              ],
              [
                -75.813059,
                39.441767
              ],
              [
                -75.813375,
                39.441729
              ],
              [
                -75.814035,
                39.441113
              ],
              [
                -75.814894,
                39.440688
              ],
              [
                -75.814891,
                39.440119
              ],
              [
                -75.815642,
                39.439909
              ],
              [
                -75.816105,
                39.440115
              ],
              [
                -75.81687,
                39.441553
              ],
              [
                -75.817256,
                39.441753
              ],
              [
                -75.818483,
                39.44164
              ],
              [
                -75.818838,
                39.441965
              ],
              [
                -75.819066,
                39.442595
              ],
              [
                -75.819824,
                39.442318
              ],
              [
                -75.82097,
                39.441282
              ],
              [
                -75.821723,
                39.44124
              ],
              [
                -75.822543,
                39.441751
              ],
              [
                -75.822995,
                39.442245
              ],
              [
                -75.823109,
                39.442678
              ],
              [
                -75.823569,
                39.443082
              ],
              [
                -75.824025,
                39.443144
              ],
              [
                -75.824172,
                39.442754
              ],
              [
                -75.824572,
                39.443004
              ],
              [
                -75.826989,
                39.442837
              ],
              [
                -75.827825,
                39.443061
              ],
              [
                -75.828812,
                39.443656
              ],
              [
                -75.830632,
                39.445604
              ],
              [
                -75.838239,
                39.44741
              ],
              [
                -75.840099,
                39.447685
              ],
              [
                -75.847313,
                39.450841
              ],
              [
                -75.854025,
                39.453158
              ],
              [
                -75.860167,
                39.453778
              ],
              [
                -75.863295,
                39.455485
              ],
              [
                -75.867298,
                39.458737
              ],
              [
                -75.871112,
                39.462206
              ],
              [
                -75.871723,
                39.463113
              ],
              [
                -75.872602,
                39.465054
              ],
              [
                -75.874009,
                39.467054
              ],
              [
                -75.877063,
                39.469808
              ],
              [
                -75.881599,
                39.472423
              ],
              [
                -75.885845,
                39.475639
              ],
              [
                -75.889342,
                39.477414
              ],
              [
                -75.894982,
                39.479212
              ],
              [
                -75.898694,
                39.480039
              ],
              [
                -75.902441,
                39.480658
              ],
              [
                -75.906358,
                39.481093
              ],
              [
                -75.909969,
                39.481236
              ],
              [
                -75.916569,
                39.480983
              ],
              [
                -75.921777,
                39.481004
              ],
              [
                -75.925307,
                39.481097
              ],
              [
                -75.929117,
                39.481652
              ],
              [
                -75.932099,
                39.48223
              ],
              [
                -75.935703,
                39.483305
              ],
              [
                -75.939035,
                39.484716
              ],
              [
                -75.937342,
                39.485952
              ],
              [
                -75.932598,
                39.490014
              ],
              [
                -75.928982,
                39.493437
              ],
              [
                -75.922489,
                39.500114
              ],
              [
                -75.923989,
                39.500114
              ],
              [
                -75.919082,
                39.505589
              ],
              [
                -75.914173,
                39.510617
              ],
              [
                -75.913282,
                39.51086
              ],
              [
                -75.90995,
                39.510061
              ],
              [
                -75.905768,
                39.510121
              ],
              [
                -75.902981,
                39.510326
              ],
              [
                -75.901872,
                39.510625
              ],
              [
                -75.898772,
                39.511008
              ],
              [
                -75.897487,
                39.511009
              ],
              [
                -75.893301,
                39.511465
              ],
              [
                -75.890741,
                39.512031
              ],
              [
                -75.888938,
                39.51275
              ],
              [
                -75.885913,
                39.516601
              ],
              [
                -75.884846,
                39.518904
              ]
            ]
          ]
        ],
        "type": "MultiPolygon"
      },
      "industries": {
        "allOther": 0,
        "goodsProducing": 0,
        "tradeTransUtil": 1
      },
      "type": "Feature",
      "workTract": "24015030200"
    },
    {
      "geometry": {
        "coordinates": [
          [
            [
              [
                -75.802383,
                39.635443
              ],
              [
                -75.796949,
                39.640168
              ],
              [
                -75.791014,
                39.639142
              ],
              [
                -75.787775,
                39.639005
              ],
              [
                -75.785127,
                39.606411
              ],
              [
                -75.790173,
                39.605413
              ],
              [
                -75.810363,
                39.599168
              ],
              [
                -75.812509,
                39.598658
              ],
              [
                -75.815035,
                39.598306
              ],
              [
                -75.818864,
                39.598248
              ],
              [
                -75.822476,
                39.598713
              ],
              [
                -75.833939,
                39.602096
              ],
              [
                -75.834072,
                39.602633
              ],
              [
                -75.833699,
                39.604068
              ],
              [
                -75.832816,
                39.604958
              ],
              [
                -75.83143,
                39.605972
              ],
              [
                -75.829996,
                39.606072
              ],
              [
                -75.828234,
                39.605508
              ],
              [
                -75.827373,
                39.604706
              ],
              [
                -75.827375,
                39.603392
              ],
              [
                -75.827243,
                39.60305
              ],
              [
                -75.826239,
                39.602918
              ],
              [
                -75.826107,
                39.603156
              ],
              [
                -75.82627,
                39.603848
              ],
              [
                -75.826208,
                39.604396
              ],
              [
                -75.825927,
                39.605122
              ],
              [
                -75.824915,
                39.606154
              ],
              [
                -75.823407,
                39.606901
              ],
              [
                -75.82292,
                39.607639
              ],
              [
                -75.821758,
                39.608723
              ],
              [
                -75.820708,
                39.60899
              ],
              [
                -75.818694,
                39.608785
              ],
              [
                -75.818241,
                39.609154
              ],
              [
                -75.817567,
                39.60932
              ],
              [
                -75.816657,
                39.609296
              ],
              [
                -75.816243,
                39.608716
              ],
              [
                -75.815697,
                39.608922
              ],
              [
                -75.815318,
                39.60931
              ],
              [
                -75.814764,
                39.609987
              ],
              [
                -75.814828,
                39.610764
              ],
              [
                -75.816116,
                39.612051
              ],
              [
                -75.81745,
                39.612193
              ],
              [
                -75.817831,
                39.61238
              ],
              [
                -75.818712,
                39.61207
              ],
              [
                -75.819403,
                39.612078
              ],
              [
                -75.82087,
                39.612763
              ],
              [
                -75.820812,
                39.61302
              ],
              [
                -75.819984,
                39.613417
              ],
              [
                -75.820146,
                39.61476
              ],
              [
                -75.819256,
                39.616486
              ],
              [
                -75.81926,
                39.616967
              ],
              [
                -75.820902,
                39.617341
              ],
              [
                -75.821649,
                39.617148
              ],
              [
                -75.824168,
                39.617693
              ],
              [
                -75.817469,
                39.622622
              ],
              [
                -75.802383,
                39.635443
              ]
            ]
          ]
        ],
        "type": "MultiPolygon"
      },
      "industries": {
        "allOther": 0,
        "goodsProducing": 0,
        "tradeTransUtil": 1
      },
      "type": "Feature",
      "workTract": "24015030506"
    },
    {
      "geometry": {
        "coordinates": [
          [
            [
              [
                -75.452855,
                39.715035
              ],
              [
                -75.450107,
                39.712326
              ],
              [
                -75.468038,
                39.696217
              ],
              [
                -75.468137,
                39.696286
              ],
              [
                -75.468989,
                39.697813
              ],
              [
                -75.469321,
                39.698831
              ],
              [
                -75.470697,
                39.71312
              ],
              [
                -75.470971,
                39.717341
              ],
              [
                -75.470304,
                39.717884
              ],
              [
                -75.467629,
                39.718937
              ],
              [
                -75.46438,
                39.719815
              ],
              [
                -75.462047,
                39.722059
              ],
              [
                -75.460917,
                39.722874
              ],
              [
                -75.452855,
                39.715035
              ]
            ]
          ]
        ],
        "type": "MultiPolygon"
      },
      "industries": {
        "allOther": 1,
        "goodsProducing": 0,
        "tradeTransUtil": 0
      },
      "type": "Feature",
      "workTract": "34033020500"
    }
  ],
  "modesOfTransport": {},
  "type": "FeatureCollection"
}
