{
  "centroid_coordinates": [],
  "features": [
    {
      "geometry": {
        "coordinates": [
          [
            [
              [
                -75.263085,
                40.287713
              ],
              [
                -75.243374,
                40.307127
              ],
              [
                -75.236395,
                40.313666
              ],
              [
                -75.235951,
                40.31385
              ],
              [
                -75.232295,
                40.311463
              ],
              [
                -75.227842,
                40.31565
              ],
              [
                -75.223809,
                40.313422
              ],
              [
                -75.221239,
                40.311242
              ],
              [
                -75.220933,
                40.309727
              ],
              [
                -75.220147,
                40.307675
              ],
              [
                -75.220583,
                40.302256
              ],
              [
                -75.220169,
                40.301113
              ],
              [
                -75.218695,
                40.299094
              ],
              [
                -75.220322,
                40.297346
              ],
              [
                -75.219035,
                40.296359
              ],
              [
                -75.223271,
                40.295232
              ],
              [
                -75.223099,
                40.29484
              ],
              [
                -75.225817,
                40.292176
              ],
              [
                -75.220299,
                40.288837
              ],
              [
                -75.218303,
                40.286486
              ],
              [
                -75.223436,
                40.281604
              ],
              [
                -75.221916,
                40.2807
              ],
              [
                -75.219965,
                40.282593
              ],
              [
                -75.217237,
                40.280948
              ],
              [
                -75.216434,
                40.281728
              ],
              [
                -75.213642,
                40.280094
              ],
              [
                -75.228425,
                40.265816
              ],
              [
                -75.252055,
                40.279466
              ],
              [
                -75.263297,
                40.286154
              ],
              [
                -75.263582,
                40.286392
              ],
              [
                -75.263551,
                40.287311
              ],
              [
                -75.263085,
                40.287713
              ]
            ]
          ]
        ],
        "type": "MultiPolygon"
      },
      "industries": {
        "allOther": 0,
        "goodsProducing": 1,
        "tradeTransUtil": 0
      },
      "type": "Feature",
      "workTract": "42017102003"
    },
    {
      "geometry": {
        "coordinates": [
          [
            [
              [
                -75.637568,
                39.983514
              ],
              [
                -75.639743,
                39.986432
              ],
              [
                -75.638581,
                39.987431
              ],
              [
                -75.633709,
                39.987799
              ],
              [
                -75.631673,
                39.988203
              ],
              [
                -75.628609,
                39.988236
              ],
              [
                -75.626288,
                39.988746
              ],
              [
                -75.623681,
                39.98886
              ],
              [
                -75.620195,
                39.989763
              ],
              [
                -75.617097,
                39.991078
              ],
              [
                -75.614281,
                39.991756
              ],
              [
                -75.613262,
                39.991827
              ],
              [
                -75.608946,
                39.993187
              ],
              [
                -75.606161,
                39.992919
              ],
              [
                -75.59717,
                39.996434
              ],
              [
                -75.596031,
                39.996379
              ],
              [
                -75.594608,
                39.99559
              ],
              [
                -75.593456,
                39.99711
              ],
              [
                -75.59312,
                39.998144
              ],
              [
                -75.583907,
                40.002001
              ],
              [
                -75.579782,
                39.996364
              ],
              [
                -75.572251,
                39.986714
              ],
              [
                -75.571388,
                39.985929
              ],
              [
                -75.570435,
                39.984366
              ],
              [
                -75.568306,
                39.98162
              ],
              [
                -75.575195,
                39.978291
              ],
              [
                -75.578894,
                39.980302
              ],
              [
                -75.582505,
                39.979588
              ],
              [
                -75.584586,
                39.978351
              ],
              [
                -75.586641,
                39.977408
              ],
              [
                -75.588126,
                39.979454
              ],
              [
                -75.590914,
                39.979314
              ],
              [
                -75.594018,
                39.977995
              ],
              [
                -75.595435,
                39.976948
              ],
              [
                -75.598543,
                39.975223
              ],
              [
                -75.60513,
                39.973736
              ],
              [
                -75.610293,
                39.970901
              ],
              [
                -75.62312,
                39.965173
              ],
              [
                -75.633515,
                39.978078
              ],
              [
                -75.637568,
                39.983514
              ]
            ]
          ]
        ],
        "type": "MultiPolygon"
      },
      "industries": {
        "allOther": 1,
        "goodsProducing": 0,
        "tradeTransUtil": 0
      },
      "type": "Feature",
      "workTract": "42029302703"
    },
    {
      "geometry": {
        "coordinates": [
          [
            [
              [
                -75.355991,
                39.963111
              ],
              [
                -75.337976,
                39.975771
              ],
              [
                -75.337422,
                39.976425
              ],
              [
                -75.337041,
                39.977352
              ],
              [
                -75.336555,
                39.977251
              ],
              [
                -75.336221,
                39.976549
              ],
              [
                -75.33616,
                39.976009
              ],
              [
                -75.336857,
                39.974926
              ],
              [
                -75.338354,
                39.973689
              ],
              [
                -75.338312,
                39.97321
              ],
              [
                -75.338545,
                39.972894
              ],
              [
                -75.338544,
                39.972623
              ],
              [
                -75.337954,
                39.971724
              ],
              [
                -75.337307,
                39.971185
              ],
              [
                -75.336599,
                39.970061
              ],
              [
                -75.334812,
                39.969238
              ],
              [
                -75.334666,
                39.969019
              ],
              [
                -75.333487,
                39.968403
              ],
              [
                -75.333486,
                39.968088
              ],
              [
                -75.33395,
                39.967141
              ],
              [
                -75.333944,
                39.965924
              ],
              [
                -75.332994,
                39.963359
              ],
              [
                -75.333402,
                39.962818
              ],
              [
                -75.333458,
                39.962277
              ],
              [
                -75.33298,
                39.960341
              ],
              [
                -75.332736,
                39.95845
              ],
              [
                -75.334427,
                39.957048
              ],
              [
                -75.334834,
                39.956461
              ],
              [
                -75.335473,
                39.955468
              ],
              [
                -75.335413,
                39.955153
              ],
              [
                -75.335132,
                39.954973
              ],
              [
                -75.337322,
                39.953652
              ],
              [
                -75.340918,
                39.950939
              ],
              [
                -75.344106,
                39.948413
              ],
              [
                -75.343839,
                39.948029
              ],
              [
                -75.347687,
                39.945352
              ],
              [
                -75.348307,
                39.945123
              ],
              [
                -75.349156,
                39.946816
              ],
              [
                -75.348946,
                39.9458
              ],
              [
                -75.348959,
                39.945423
              ],
              [
                -75.349093,
                39.94534
              ],
              [
                -75.349176,
                39.946534
              ],
              [
                -75.349815,
                39.948012
              ],
              [
                -75.357775,
                39.963744
              ],
              [
                -75.357657,
                39.963851
              ],
              [
                -75.35691,
                39.962478
              ],
              [
                -75.355991,
                39.963111
              ]
            ]
          ]
        ],
        "type": "MultiPolygon"
      },
      "industries": {
        "allOther": 1,
        "goodsProducing": 0,
        "tradeTransUtil": 0
      },
      "type": "Feature",
      "workTract": "42045408103"
    },
    {
      "geometry": {
        "coordinates": [
          [
            [
              [
                -75.386343,
                40.005215
              ],
              [
                -75.388801,
                40.008012
              ],
              [
                -75.390113,
                40.009896
              ],
              [
                -75.391851,
                40.011926
              ],
              [
                -75.394551,
                40.015498
              ],
              [
                -75.400135,
                40.022421
              ],
              [
                -75.401314,
                40.023687
              ],
              [
                -75.398866,
                40.023021
              ],
              [
                -75.395847,
                40.023341
              ],
              [
                -75.396414,
                40.025796
              ],
              [
                -75.396398,
                40.026572
              ],
              [
                -75.39513,
                40.028034
              ],
              [
                -75.394116,
                40.028692
              ],
              [
                -75.38169,
                40.033986
              ],
              [
                -75.381062,
                40.03462
              ],
              [
                -75.380291,
                40.034976
              ],
              [
                -75.377553,
                40.035615
              ],
              [
                -75.372296,
                40.037757
              ],
              [
                -75.370569,
                40.037899
              ],
              [
                -75.366516,
                40.039791
              ],
              [
                -75.365745,
                40.039429
              ],
              [
                -75.365071,
                40.040224
              ],
              [
                -75.359806,
                40.042594
              ],
              [
                -75.359051,
                40.0436
              ],
              [
                -75.361506,
                40.046366
              ],
              [
                -75.360255,
                40.046708
              ],
              [
                -75.356465,
                40.046936
              ],
              [
                -75.354047,
                40.04806
              ],
              [
                -75.352475,
                40.049035
              ],
              [
                -75.351618,
                40.049788
              ],
              [
                -75.350752,
                40.050164
              ],
              [
                -75.350546,
                40.050919
              ],
              [
                -75.350671,
                40.052168
              ],
              [
                -75.350316,
                40.052515
              ],
              [
                -75.349457,
                40.052905
              ],
              [
                -75.340149,
                40.041431
              ],
              [
                -75.339396,
                40.040323
              ],
              [
                -75.342194,
                40.038973
              ],
              [
                -75.349344,
                40.035939
              ],
              [
                -75.343646,
                40.034946
              ],
              [
                -75.343848,
                40.034038
              ],
              [
                -75.342257,
                40.033695
              ],
              [
                -75.340992,
                40.032907
              ],
              [
                -75.357833,
                40.025578
              ],
              [
                -75.358455,
                40.025165
              ],
              [
                -75.360566,
                40.02282
              ],
              [
                -75.360537,
                40.022542
              ],
              [
                -75.35871,
                40.019884
              ],
              [
                -75.358011,
                40.018407
              ],
              [
                -75.357017,
                40.017604
              ],
              [
                -75.356481,
                40.016788
              ],
              [
                -75.356285,
                40.016245
              ],
              [
                -75.356585,
                40.014879
              ],
              [
                -75.354705,
                40.013383
              ],
              [
                -75.354488,
                40.01301
              ],
              [
                -75.354258,
                40.011331
              ],
              [
                -75.354353,
                40.010704
              ],
              [
                -75.353674,
                40.009547
              ],
              [
                -75.353631,
                40.00718
              ],
              [
                -75.353741,
                40.007166
              ],
              [
                -75.353196,
                40.006285
              ],
              [
                -75.352623,
                40.005854
              ],
              [
                -75.352681,
                40.0055
              ],
              [
                -75.352488,
                40.005193
              ],
              [
                -75.352545,
                40.004698
              ],
              [
                -75.353358,
                40.003616
              ],
              [
                -75.353958,
                40.003446
              ],
              [
                -75.353744,
                40.003056
              ],
              [
                -75.353986,
                40.002457
              ],
              [
                -75.353584,
                40.002132
              ],
              [
                -75.35618,
                40.000792
              ],
              [
                -75.362937,
                39.998018
              ],
              [
                -75.369254,
                39.995101
              ],
              [
                -75.370929,
                39.993845
              ],
              [
                -75.37409,
                39.990181
              ],
              [
                -75.38528,
                40.003689
              ],
              [
                -75.386343,
                40.005215
              ]
            ]
          ]
        ],
        "type": "MultiPolygon"
      },
      "industries": {
        "allOther": 1,
        "goodsProducing": 0,
        "tradeTransUtil": 0
      },
      "type": "Feature",
      "workTract": "42045409701"
    },
    {
      "geometry": {
        "coordinates": [
          [
            [
              [
                -75.05947,
                40.05225
              ],
              [
                -75.060654,
                40.050999
              ],
              [
                -75.058284,
                40.049688
              ],
              [
                -75.059937,
                40.047751
              ],
              [
                -75.073256,
                40.05533
              ],
              [
                -75.068074,
                40.060824
              ],
              [
                -75.057125,
                40.054722
              ],
              [
                -75.05947,
                40.05225
              ]
            ]
          ]
        ],
        "type": "MultiPolygon"
      },
      "industries": {
        "allOther": 0,
        "goodsProducing": 0,
        "tradeTransUtil": 1
      },
      "type": "Feature",
      "workTract": "42101033500"
    },
    {
      "geometry": {
        "coordinates": [
          [
            [
              [
                -75.141469,
                39.951698
              ],
              [
                -75.141625,
                39.955279
              ],
              [
                -75.141412,
                39.957117
              ],
              [
                -75.139954,
                39.956928
              ],
              [
                -75.138081,
                39.962936
              ],
              [
                -75.136755,
                39.962766
              ],
              [
                -75.135338,
                39.96184
              ],
              [
                -75.133635,
                39.961296
              ],
              [
                -75.130404,
                39.958737
              ],
              [
                -75.131777,
                39.957319
              ],
              [
                -75.133698,
                39.95462
              ],
              [
                -75.135239,
                39.950677
              ],
              [
                -75.136268,
                39.943282
              ],
              [
                -75.136062,
                39.934495
              ],
              [
                -75.136151,
                39.932974
              ],
              [
                -75.135539,
                39.929237
              ],
              [
                -75.137217,
                39.928886
              ],
              [
                -75.140822,
                39.929192
              ],
              [
                -75.141006,
                39.929379
              ],
              [
                -75.146413,
                39.930114
              ],
              [
                -75.145702,
                39.933438
              ],
              [
                -75.145146,
                39.933321
              ],
              [
                -75.144588,
                39.935627
              ],
              [
                -75.143467,
                39.938725
              ],
              [
                -75.144529,
                39.938873
              ],
              [
                -75.142466,
                39.948174
              ],
              [
                -75.142052,
                39.948122
              ],
              [
                -75.141469,
                39.951698
              ]
            ]
          ]
        ],
        "type": "MultiPolygon"
      },
      "industries": {
        "allOther": 1,
        "goodsProducing": 0,
        "tradeTransUtil": 0
      },
      "type": "Feature",
      "workTract": "42101036600"
    },
    {
      "geometry": {
        "coordinates": [
          [
            [
              [
                -75.752653,
                39.66588
              ],
              [
                -75.753025,
                39.670109
              ],
              [
                -75.75345,
                39.672117
              ],
              [
                -75.753672,
                39.683014
              ],
              [
                -75.738335,
                39.684275
              ],
              [
                -75.736474,
                39.6845
              ],
              [
                -75.732959,
                39.685373
              ],
              [
                -75.729153,
                39.677472
              ],
              [
                -75.736245,
                39.675276
              ],
              [
                -75.738417,
                39.671333
              ],
              [
                -75.738878,
                39.669402
              ],
              [
                -75.738688,
                39.667747
              ],
              [
                -75.738296,
                39.666523
              ],
              [
                -75.735994,
                39.661576
              ],
              [
                -75.737929,
                39.661155
              ],
              [
                -75.744111,
                39.658958
              ],
              [
                -75.747134,
                39.658305
              ],
              [
                -75.748396,
                39.658228
              ],
              [
                -75.748649,
                39.657614
              ],
              [
                -75.751308,
                39.655748
              ],
              [
                -75.751659,
                39.659382
              ],
              [
                -75.752079,
                39.661411
              ],
              [
                -75.752653,
                39.66588
              ]
            ]
          ]
        ],
        "type": "MultiPolygon"
      },
      "industries": {
        "allOther": 3,
        "goodsProducing": 0,
        "tradeTransUtil": 0
      },
      "type": "Feature",
      "workTract": "10003014502"
    },
    {
      "geometry": {
        "coordinates": [
          [
            [
              [
                -75.116518,
                39.903491
              ],
              [
                -75.116367,
                39.903985
              ],
              [
                -75.116571,
                39.903959
              ],
              [
                -75.116651,
                39.903613
              ],
              [
                -75.116725,
                39.904024
              ],
              [
                -75.116197,
                39.904206
              ],
              [
                -75.11571,
                39.905502
              ],
              [
                -75.115622,
                39.90622
              ],
              [
                -75.116271,
                39.906723
              ],
              [
                -75.116224,
                39.907042
              ],
              [
                -75.117177,
                39.908189
              ],
              [
                -75.117911,
                39.908622
              ],
              [
                -75.12036,
                39.908472
              ],
              [
                -75.122029,
                39.907458
              ],
              [
                -75.12509,
                39.907293
              ],
              [
                -75.128887,
                39.907446
              ],
              [
                -75.128537,
                39.909095
              ],
              [
                -75.128253,
                39.913164
              ],
              [
                -75.129342,
                39.9159
              ],
              [
                -75.13035,
                39.917404
              ],
              [
                -75.134484,
                39.926168
              ],
              [
                -75.134896,
                39.927351
              ],
              [
                -75.130645,
                39.927667
              ],
              [
                -75.126809,
                39.928175
              ],
              [
                -75.113138,
                39.929141
              ],
              [
                -75.115804,
                39.926576
              ],
              [
                -75.116474,
                39.925525
              ],
              [
                -75.116639,
                39.92474
              ],
              [
                -75.117584,
                39.912644
              ],
              [
                -75.115813,
                39.912621
              ],
              [
                -75.115563,
                39.911266
              ],
              [
                -75.113831,
                39.90685
              ],
              [
                -75.114667,
                39.906646
              ],
              [
                -75.116518,
                39.903491
              ]
            ]
          ]
        ],
        "type": "MultiPolygon"
      },
      "industries": {
        "allOther": 0,
        "goodsProducing": 0,
        "tradeTransUtil": 1
      },
      "type": "Feature",
      "workTract": "34007601800"
    },
    {
      "geometry": {
        "coordinates": [
          [
            [
              [
                -75.034642,
                39.89672
              ],
              [
                -75.035927,
                39.896111
              ],
              [
                -75.039382,
                39.901571
              ],
              [
                -75.040005,
                39.902298
              ],
              [
                -75.042019,
                39.904036
              ],
              [
                -75.041578,
                39.904674
              ],
              [
                -75.042963,
                39.905734
              ],
              [
                -75.042649,
                39.907884
              ],
              [
                -75.039283,
                39.908063
              ],
              [
                -75.039438,
                39.909209
              ],
              [
                -75.038995,
                39.909233
              ],
              [
                -75.037948,
                39.909983
              ],
              [
                -75.037615,
                39.910413
              ],
              [
                -75.042361,
                39.911961
              ],
              [
                -75.041154,
                39.913873
              ],
              [
                -75.042606,
                39.91431
              ],
              [
                -75.04249,
                39.916173
              ],
              [
                -75.039869,
                39.915773
              ],
              [
                -75.039347,
                39.916515
              ],
              [
                -75.035114,
                39.915903
              ],
              [
                -75.034631,
                39.916013
              ],
              [
                -75.034632,
                39.915798
              ],
              [
                -75.033695,
                39.916045
              ],
              [
                -75.032093,
                39.915719
              ],
              [
                -75.031332,
                39.915714
              ],
              [
                -75.031141,
                39.915593
              ],
              [
                -75.030628,
                39.914232
              ],
              [
                -75.030007,
                39.913593
              ],
              [
                -75.029892,
                39.913164
              ],
              [
                -75.030076,
                39.913084
              ],
              [
                -75.028494,
                39.91217
              ],
              [
                -75.027931,
                39.912197
              ],
              [
                -75.027455,
                39.911998
              ],
              [
                -75.026904,
                39.911675
              ],
              [
                -75.026478,
                39.91117
              ],
              [
                -75.02667,
                39.909292
              ],
              [
                -75.026579,
                39.908173
              ],
              [
                -75.027046,
                39.906782
              ],
              [
                -75.026372,
                39.906521
              ],
              [
                -75.026194,
                39.906341
              ],
              [
                -75.026115,
                39.905819
              ],
              [
                -75.024953,
                39.905116
              ],
              [
                -75.024369,
                39.904503
              ],
              [
                -75.023407,
                39.904612
              ],
              [
                -75.022864,
                39.904486
              ],
              [
                -75.022494,
                39.904261
              ],
              [
                -75.022408,
                39.90354
              ],
              [
                -75.022052,
                39.903612
              ],
              [
                -75.022074,
                39.903338
              ],
              [
                -75.022288,
                39.903178
              ],
              [
                -75.024539,
                39.901922
              ],
              [
                -75.034642,
                39.89672
              ]
            ]
          ]
        ],
        "type": "MultiPolygon"
      },
      "industries": {
        "allOther": 1,
        "goodsProducing": 0,
        "tradeTransUtil": 0
      },
      "type": "Feature",
      "workTract": "34007606200"
    }
  ],
  "modesOfTransport": {},
  "type": "FeatureCollection"
}
