{
  "centroid_coordinates": [],
  "features": [
    {
      "geometry": {
        "coordinates": [
          [
            [
              [
                -74.837461,
                40.111031
              ],
              [
                -74.841312,
                40.115973
              ],
              [
                -74.841647,
                40.115539
              ],
              [
                -74.842305,
                40.116411
              ],
              [
                -74.841163,
                40.116945
              ],
              [
                -74.841823,
                40.117244
              ],
              [
                -74.842659,
                40.116874
              ],
              [
                -74.843473,
                40.117951
              ],
              [
                -74.843555,
                40.117586
              ],
              [
                -74.844026,
                40.117001
              ],
              [
                -74.848847,
                40.112412
              ],
              [
                -74.849667,
                40.109941
              ],
              [
                -74.852101,
                40.111151
              ],
              [
                -74.853653,
                40.111321
              ],
              [
                -74.857653,
                40.110036
              ],
              [
                -74.860719,
                40.108396
              ],
              [
                -74.860982,
                40.107122
              ],
              [
                -74.861561,
                40.105875
              ],
              [
                -74.861302,
                40.104788
              ],
              [
                -74.861497,
                40.103955
              ],
              [
                -74.861314,
                40.102015
              ],
              [
                -74.863996,
                40.103475
              ],
              [
                -74.864233,
                40.103359
              ],
              [
                -74.864745,
                40.104446
              ],
              [
                -74.86599,
                40.103853
              ],
              [
                -74.867312,
                40.104048
              ],
              [
                -74.866816,
                40.104326
              ],
              [
                -74.869219,
                40.105812
              ],
              [
                -74.870932,
                40.106565
              ],
              [
                -74.870689,
                40.105772
              ],
              [
                -74.872071,
                40.103711
              ],
              [
                -74.874896,
                40.102375
              ],
              [
                -74.88085,
                40.115361
              ],
              [
                -74.881097,
                40.116804
              ],
              [
                -74.8818,
                40.125164
              ],
              [
                -74.882279,
                40.127741
              ],
              [
                -74.85408,
                40.123559
              ],
              [
                -74.830592,
                40.117015
              ],
              [
                -74.833103,
                40.111972
              ],
              [
                -74.833964,
                40.107809
              ],
              [
                -74.837018,
                40.109093
              ],
              [
                -74.836737,
                40.109957
              ],
              [
                -74.837461,
                40.111031
              ]
            ]
          ]
        ],
        "type": "MultiPolygon"
      },
      "industries": {
        "allOther": 0,
        "goodsProducing": 0,
        "tradeTransUtil": 1
      },
      "type": "Feature",
      "workTract": "42017100303"
    },
    {
      "geometry": {
        "coordinates": [
          [
            [
              [
                -75.255617,
                40.429118
              ],
              [
                -75.255218,
                40.429114
              ],
              [
                -75.255209,
                40.429232
              ],
              [
                -75.254477,
                40.429413
              ],
              [
                -75.254071,
                40.429653
              ],
              [
                -75.253884,
                40.42999
              ],
              [
                -75.253787,
                40.430415
              ],
              [
                -75.255102,
                40.432656
              ],
              [
                -75.254454,
                40.434337
              ],
              [
                -75.254045,
                40.434989
              ],
              [
                -75.253285,
                40.435419
              ],
              [
                -75.251201,
                40.436154
              ],
              [
                -75.24921,
                40.436559
              ],
              [
                -75.248101,
                40.437362
              ],
              [
                -75.247375,
                40.438479
              ],
              [
                -75.242921,
                40.440496
              ],
              [
                -75.240803,
                40.441711
              ],
              [
                -75.240264,
                40.442736
              ],
              [
                -75.240463,
                40.444459
              ],
              [
                -75.239696,
                40.446073
              ],
              [
                -75.238171,
                40.447467
              ],
              [
                -75.239183,
                40.447977
              ],
              [
                -75.238973,
                40.448906
              ],
              [
                -75.238079,
                40.449831
              ],
              [
                -75.235245,
                40.450419
              ],
              [
                -75.233412,
                40.450975
              ],
              [
                -75.232851,
                40.451903
              ],
              [
                -75.233383,
                40.453181
              ],
              [
                -75.234207,
                40.454546
              ],
              [
                -75.232941,
                40.456332
              ],
              [
                -75.230804,
                40.458056
              ],
              [
                -75.230316,
                40.45862
              ],
              [
                -75.230576,
                40.459895
              ],
              [
                -75.229996,
                40.461443
              ],
              [
                -75.229141,
                40.462801
              ],
              [
                -75.227814,
                40.463305
              ],
              [
                -75.226578,
                40.464358
              ],
              [
                -75.22467,
                40.464571
              ],
              [
                -75.221542,
                40.464434
              ],
              [
                -75.21875,
                40.464564
              ],
              [
                -75.218796,
                40.465548
              ],
              [
                -75.218399,
                40.467936
              ],
              [
                -75.216248,
                40.469836
              ],
              [
                -75.212387,
                40.470301
              ],
              [
                -75.207275,
                40.468745
              ],
              [
                -75.201507,
                40.469096
              ],
              [
                -75.199965,
                40.471621
              ],
              [
                -75.198501,
                40.471812
              ],
              [
                -75.195464,
                40.471331
              ],
              [
                -75.194259,
                40.47188
              ],
              [
                -75.193725,
                40.473124
              ],
              [
                -75.193999,
                40.475253
              ],
              [
                -75.19197,
                40.475153
              ],
              [
                -75.189452,
                40.474024
              ],
              [
                -75.188979,
                40.472674
              ],
              [
                -75.187507,
                40.470104
              ],
              [
                -75.186619,
                40.469441
              ],
              [
                -75.182765,
                40.469232
              ],
              [
                -75.182196,
                40.469075
              ],
              [
                -75.180635,
                40.468298
              ],
              [
                -75.179632,
                40.467984
              ],
              [
                -75.179277,
                40.467535
              ],
              [
                -75.178509,
                40.46713
              ],
              [
                -75.177681,
                40.466321
              ],
              [
                -75.176088,
                40.466188
              ],
              [
                -75.175556,
                40.465783
              ],
              [
                -75.175553,
                40.464477
              ],
              [
                -75.175375,
                40.464162
              ],
              [
                -75.17319,
                40.462949
              ],
              [
                -75.168235,
                40.462371
              ],
              [
                -75.164399,
                40.461386
              ],
              [
                -75.161745,
                40.461479
              ],
              [
                -75.161273,
                40.461165
              ],
              [
                -75.161151,
                40.459498
              ],
              [
                -75.159023,
                40.457744
              ],
              [
                -75.158076,
                40.456259
              ],
              [
                -75.157013,
                40.455585
              ],
              [
                -75.15701,
                40.454009
              ],
              [
                -75.156299,
                40.452703
              ],
              [
                -75.156357,
                40.452253
              ],
              [
                -75.15983,
                40.450375
              ],
              [
                -75.162185,
                40.4481
              ],
              [
                -75.163538,
                40.447017
              ],
              [
                -75.163359,
                40.446297
              ],
              [
                -75.163957,
                40.445532
              ],
              [
                -75.163947,
                40.44535
              ],
              [
                -75.163001,
                40.44427
              ],
              [
                -75.162527,
                40.44328
              ],
              [
                -75.162172,
                40.44301
              ],
              [
                -75.159222,
                40.442023
              ],
              [
                -75.15822,
                40.44198
              ],
              [
                -75.157453,
                40.441756
              ],
              [
                -75.156274,
                40.441757
              ],
              [
                -75.15527,
                40.441398
              ],
              [
                -75.154445,
                40.441444
              ],
              [
                -75.152266,
                40.442483
              ],
              [
                -75.149851,
                40.443387
              ],
              [
                -75.148084,
                40.444291
              ],
              [
                -75.146966,
                40.445238
              ],
              [
                -75.146377,
                40.445464
              ],
              [
                -75.145669,
                40.445465
              ],
              [
                -75.144606,
                40.444655
              ],
              [
                -75.143662,
                40.444296
              ],
              [
                -75.143012,
                40.443756
              ],
              [
                -75.142539,
                40.443036
              ],
              [
                -75.14177,
                40.441551
              ],
              [
                -75.141236,
                40.43993
              ],
              [
                -75.141234,
                40.437512
              ],
              [
                -75.140563,
                40.436611
              ],
              [
                -75.139276,
                40.43541
              ],
              [
                -75.138208,
                40.435076
              ],
              [
                -75.137749,
                40.434704
              ],
              [
                -75.135623,
                40.434912
              ],
              [
                -75.13382,
                40.435311
              ],
              [
                -75.129739,
                40.436873
              ],
              [
                -75.126017,
                40.437922
              ],
              [
                -75.124074,
                40.438269
              ],
              [
                -75.123231,
                40.437811
              ],
              [
                -75.121872,
                40.43601
              ],
              [
                -75.12075,
                40.434885
              ],
              [
                -75.119334,
                40.434256
              ],
              [
                -75.116552,
                40.433727
              ],
              [
                -75.132823,
                40.416905
              ],
              [
                -75.135164,
                40.414651
              ],
              [
                -75.134624,
                40.412658
              ],
              [
                -75.135892,
                40.412315
              ],
              [
                -75.140464,
                40.408053
              ],
              [
                -75.140634,
                40.407235
              ],
              [
                -75.146597,
                40.402275
              ],
              [
                -75.150006,
                40.400047
              ],
              [
                -75.149313,
                40.398282
              ],
              [
                -75.154704,
                40.393082
              ],
              [
                -75.155265,
                40.393573
              ],
              [
                -75.156981,
                40.392331
              ],
              [
                -75.160064,
                40.388972
              ],
              [
                -75.161776,
                40.390002
              ],
              [
                -75.162106,
                40.38997
              ],
              [
                -75.188177,
                40.364272
              ],
              [
                -75.188832,
                40.363347
              ],
              [
                -75.190674,
                40.364116
              ],
              [
                -75.197144,
                40.368104
              ],
              [
                -75.195217,
                40.369934
              ],
              [
                -75.195788,
                40.370301
              ],
              [
                -75.193766,
                40.372203
              ],
              [
                -75.200441,
                40.376243
              ],
              [
                -75.203892,
                40.379274
              ],
              [
                -75.204357,
                40.382727
              ],
              [
                -75.210644,
                40.376442
              ],
              [
                -75.216612,
                40.380403
              ],
              [
                -75.244761,
                40.397942
              ],
              [
                -75.247032,
                40.401261
              ],
              [
                -75.247893,
                40.403912
              ],
              [
                -75.248638,
                40.40466
              ],
              [
                -75.250162,
                40.407122
              ],
              [
                -75.251822,
                40.412336
              ],
              [
                -75.252569,
                40.416516
              ],
              [
                -75.253743,
                40.419621
              ],
              [
                -75.25542,
                40.427408
              ],
              [
                -75.255617,
                40.429118
              ]
            ]
          ]
        ],
        "type": "MultiPolygon"
      },
      "industries": {
        "allOther": 0,
        "goodsProducing": 1,
        "tradeTransUtil": 0
      },
      "type": "Feature",
      "workTract": "42017104000"
    },
    {
      "geometry": {
        "coordinates": [
          [
            [
              [
                -74.956196,
                40.216235
              ],
              [
                -74.956255,
                40.216685
              ],
              [
                -74.956666,
                40.217496
              ],
              [
                -74.957194,
                40.218127
              ],
              [
                -74.958193,
                40.218893
              ],
              [
                -74.959368,
                40.219524
              ],
              [
                -74.961776,
                40.220426
              ],
              [
                -74.964009,
                40.220652
              ],
              [
                -74.965067,
                40.221238
              ],
              [
                -74.96536,
                40.221598
              ],
              [
                -74.96536,
                40.222139
              ],
              [
                -74.964269,
                40.224092
              ],
              [
                -74.957989,
                40.22518
              ],
              [
                -74.953348,
                40.225566
              ],
              [
                -74.947993,
                40.226506
              ],
              [
                -74.938178,
                40.227936
              ],
              [
                -74.938209,
                40.227413
              ],
              [
                -74.938668,
                40.22621
              ],
              [
                -74.938546,
                40.225161
              ],
              [
                -74.938919,
                40.224535
              ],
              [
                -74.938159,
                40.223513
              ],
              [
                -74.93819,
                40.222013
              ],
              [
                -74.934615,
                40.220947
              ],
              [
                -74.934459,
                40.220665
              ],
              [
                -74.931782,
                40.221306
              ],
              [
                -74.931405,
                40.2242
              ],
              [
                -74.925633,
                40.225186
              ],
              [
                -74.925269,
                40.228771
              ],
              [
                -74.921887,
                40.229062
              ],
              [
                -74.918394,
                40.230124
              ],
              [
                -74.916068,
                40.230648
              ],
              [
                -74.907953,
                40.231246
              ],
              [
                -74.907105,
                40.231206
              ],
              [
                -74.906104,
                40.230933
              ],
              [
                -74.903523,
                40.229365
              ],
              [
                -74.901992,
                40.230862
              ],
              [
                -74.900308,
                40.231632
              ],
              [
                -74.898973,
                40.231891
              ],
              [
                -74.893747,
                40.232374
              ],
              [
                -74.887906,
                40.225691
              ],
              [
                -74.887551,
                40.224735
              ],
              [
                -74.902454,
                40.22134
              ],
              [
                -74.910629,
                40.222041
              ],
              [
                -74.917038,
                40.220895
              ],
              [
                -74.927538,
                40.218243
              ],
              [
                -74.929343,
                40.217636
              ],
              [
                -74.94331,
                40.214175
              ],
              [
                -74.94441,
                40.211453
              ],
              [
                -74.94527,
                40.21168
              ],
              [
                -74.953085,
                40.211503
              ],
              [
                -74.954436,
                40.211909
              ],
              [
                -74.955141,
                40.21254
              ],
              [
                -74.955258,
                40.213937
              ],
              [
                -74.956196,
                40.216235
              ]
            ]
          ]
        ],
        "type": "MultiPolygon"
      },
      "industries": {
        "allOther": 1,
        "goodsProducing": 0,
        "tradeTransUtil": 0
      },
      "type": "Feature",
      "workTract": "42017105202"
    },
    {
      "geometry": {
        "coordinates": [
          [
            [
              [
                -74.93789,
                40.232717
              ],
              [
                -74.937323,
                40.232686
              ],
              [
                -74.937947,
                40.227939
              ],
              [
                -74.947993,
                40.226506
              ],
              [
                -74.953348,
                40.225566
              ],
              [
                -74.957317,
                40.225279
              ],
              [
                -74.964269,
                40.224092
              ],
              [
                -74.963008,
                40.225427
              ],
              [
                -74.962772,
                40.226012
              ],
              [
                -74.962831,
                40.226868
              ],
              [
                -74.966061,
                40.229842
              ],
              [
                -74.967589,
                40.230293
              ],
              [
                -74.972291,
                40.230835
              ],
              [
                -74.973878,
                40.231736
              ],
              [
                -74.974406,
                40.232367
              ],
              [
                -74.974406,
                40.232998
              ],
              [
                -74.9737,
                40.234124
              ],
              [
                -74.971584,
                40.235565
              ],
              [
                -74.971113,
                40.236285
              ],
              [
                -74.970113,
                40.238673
              ],
              [
                -74.969936,
                40.239348
              ],
              [
                -74.969936,
                40.240339
              ],
              [
                -74.970288,
                40.240565
              ],
              [
                -74.971053,
                40.240655
              ],
              [
                -74.973228,
                40.24061
              ],
              [
                -74.975595,
                40.239744
              ],
              [
                -74.977093,
                40.240498
              ],
              [
                -74.978269,
                40.240754
              ],
              [
                -74.978539,
                40.240952
              ],
              [
                -74.979458,
                40.242459
              ],
              [
                -74.979458,
                40.243405
              ],
              [
                -74.981632,
                40.244982
              ],
              [
                -74.982867,
                40.245657
              ],
              [
                -74.983631,
                40.245883
              ],
              [
                -74.984355,
                40.246349
              ],
              [
                -74.98561,
                40.246299
              ],
              [
                -74.969318,
                40.262524
              ],
              [
                -74.965876,
                40.260303
              ],
              [
                -74.957646,
                40.254238
              ],
              [
                -74.946814,
                40.239258
              ],
              [
                -74.946376,
                40.238387
              ],
              [
                -74.945895,
                40.236396
              ],
              [
                -74.943864,
                40.236434
              ],
              [
                -74.937362,
                40.236054
              ],
              [
                -74.93789,
                40.232717
              ]
            ]
          ]
        ],
        "type": "MultiPolygon"
      },
      "industries": {
        "allOther": 1,
        "goodsProducing": 0,
        "tradeTransUtil": 0
      },
      "type": "Feature",
      "workTract": "42017105203"
    },
    {
      "geometry": {
        "coordinates": [
          [
            [
              [
                -74.810607,
                40.126414
              ],
              [
                -74.813883,
                40.127362
              ],
              [
                -74.815625,
                40.127705
              ],
              [
                -74.822396,
                40.13646
              ],
              [
                -74.828752,
                40.145375
              ],
              [
                -74.823159,
                40.14795
              ],
              [
                -74.82245,
                40.147063
              ],
              [
                -74.816498,
                40.14979
              ],
              [
                -74.818291,
                40.151884
              ],
              [
                -74.819852,
                40.151337
              ],
              [
                -74.820762,
                40.153212
              ],
              [
                -74.819081,
                40.153676
              ],
              [
                -74.820561,
                40.155404
              ],
              [
                -74.815374,
                40.155673
              ],
              [
                -74.815737,
                40.156229
              ],
              [
                -74.813028,
                40.156359
              ],
              [
                -74.814213,
                40.149133
              ],
              [
                -74.810723,
                40.148725
              ],
              [
                -74.809294,
                40.151948
              ],
              [
                -74.805792,
                40.151135
              ],
              [
                -74.806502,
                40.149902
              ],
              [
                -74.806331,
                40.148995
              ],
              [
                -74.804849,
                40.150351
              ],
              [
                -74.802401,
                40.150493
              ],
              [
                -74.802216,
                40.145188
              ],
              [
                -74.796128,
                40.146941
              ],
              [
                -74.794807,
                40.133812
              ],
              [
                -74.796709,
                40.13321
              ],
              [
                -74.800724,
                40.132925
              ],
              [
                -74.802653,
                40.13258
              ],
              [
                -74.804749,
                40.131816
              ],
              [
                -74.804815,
                40.125808
              ],
              [
                -74.805293,
                40.124529
              ],
              [
                -74.810607,
                40.126414
              ]
            ]
          ]
        ],
        "type": "MultiPolygon"
      },
      "industries": {
        "allOther": 1,
        "goodsProducing": 0,
        "tradeTransUtil": 0
      },
      "type": "Feature",
      "workTract": "42017105900"
    },
    {
      "geometry": {
        "coordinates": [
          [
            [
              [
                -75.596419,
                40.055807
              ],
              [
                -75.550616,
                40.070219
              ],
              [
                -75.53009,
                40.074983
              ],
              [
                -75.523558,
                40.0662
              ],
              [
                -75.507943,
                40.04667
              ],
              [
                -75.517006,
                40.044626
              ],
              [
                -75.540578,
                40.040068
              ],
              [
                -75.553906,
                40.036884
              ],
              [
                -75.566137,
                40.034981
              ],
              [
                -75.569163,
                40.0341
              ],
              [
                -75.575388,
                40.031599
              ],
              [
                -75.584689,
                40.029602
              ],
              [
                -75.589387,
                40.036115
              ],
              [
                -75.588331,
                40.036506
              ],
              [
                -75.588757,
                40.037263
              ],
              [
                -75.60131,
                40.054316
              ],
              [
                -75.596419,
                40.055807
              ]
            ]
          ]
        ],
        "type": "MultiPolygon"
      },
      "industries": {
        "allOther": 1,
        "goodsProducing": 0,
        "tradeTransUtil": 0
      },
      "type": "Feature",
      "workTract": "42029302101"
    },
    {
      "geometry": {
        "coordinates": [
          [
            [
              [
                -75.587632,
                39.940078
              ],
              [
                -75.57223,
                39.947346
              ],
              [
                -75.570175,
                39.948027
              ],
              [
                -75.559394,
                39.952869
              ],
              [
                -75.552727,
                39.944322
              ],
              [
                -75.546685,
                39.936179
              ],
              [
                -75.544903,
                39.9343
              ],
              [
                -75.596808,
                39.91082
              ],
              [
                -75.60071,
                39.916114
              ],
              [
                -75.607459,
                39.924354
              ],
              [
                -75.610783,
                39.928709
              ],
              [
                -75.610076,
                39.929624
              ],
              [
                -75.587632,
                39.940078
              ]
            ]
          ]
        ],
        "type": "MultiPolygon"
      },
      "industries": {
        "allOther": 1,
        "goodsProducing": 0,
        "tradeTransUtil": 0
      },
      "type": "Feature",
      "workTract": "42029302902"
    },
    {
      "geometry": {
        "coordinates": [
          [
            [
              [
                -75.263467,
                39.878226
              ],
              [
                -75.262528,
                39.876561
              ],
              [
                -75.252257,
                39.875937
              ],
              [
                -75.248431,
                39.876485
              ],
              [
                -75.246824,
                39.875142
              ],
              [
                -75.249903,
                39.874665
              ],
              [
                -75.251681,
                39.873862
              ],
              [
                -75.259802,
                39.872294
              ],
              [
                -75.261123,
                39.872463
              ],
              [
                -75.264532,
                39.874588
              ],
              [
                -75.265744,
                39.874872
              ],
              [
                -75.266834,
                39.874748
              ],
              [
                -75.270139,
                39.873556
              ],
              [
                -75.271084,
                39.872819
              ],
              [
                -75.271369,
                39.872244
              ],
              [
                -75.271373,
                39.871668
              ],
              [
                -75.270053,
                39.867367
              ],
              [
                -75.270043,
                39.866745
              ],
              [
                -75.268609,
                39.864756
              ],
              [
                -75.276904,
                39.863685
              ],
              [
                -75.26807,
                39.849831
              ],
              [
                -75.272202,
                39.849076
              ],
              [
                -75.274762,
                39.848978
              ],
              [
                -75.27911,
                39.849141
              ],
              [
                -75.286907,
                39.848843
              ],
              [
                -75.289638,
                39.848927
              ],
              [
                -75.293376,
                39.848782
              ],
              [
                -75.300122,
                39.849248
              ],
              [
                -75.309674,
                39.850178
              ],
              [
                -75.316531,
                39.850012
              ],
              [
                -75.314732,
                39.857212
              ],
              [
                -75.301308,
                39.856715
              ],
              [
                -75.295188,
                39.857072
              ],
              [
                -75.295091,
                39.860542
              ],
              [
                -75.293234,
                39.860466
              ],
              [
                -75.292984,
                39.863805
              ],
              [
                -75.293897,
                39.863842
              ],
              [
                -75.293762,
                39.865562
              ],
              [
                -75.294667,
                39.865923
              ],
              [
                -75.294197,
                39.872534
              ],
              [
                -75.294403,
                39.872974
              ],
              [
                -75.301341,
                39.870763
              ],
              [
                -75.304927,
                39.876761
              ],
              [
                -75.299841,
                39.877301
              ],
              [
                -75.298319,
                39.876792
              ],
              [
                -75.297313,
                39.875204
              ],
              [
                -75.295483,
                39.875314
              ],
              [
                -75.294922,
                39.876134
              ],
              [
                -75.293918,
                39.876778
              ],
              [
                -75.293459,
                39.877466
              ],
              [
                -75.291186,
                39.879184
              ],
              [
                -75.289611,
                39.879999
              ],
              [
                -75.288386,
                39.880858
              ],
              [
                -75.287947,
                39.880454
              ],
              [
                -75.283945,
                39.881454
              ],
              [
                -75.28196,
                39.881573
              ],
              [
                -75.279951,
                39.880848
              ],
              [
                -75.276398,
                39.880686
              ],
              [
                -75.275273,
                39.879353
              ],
              [
                -75.274795,
                39.877413
              ],
              [
                -75.274439,
                39.877024
              ],
              [
                -75.27341,
                39.876692
              ],
              [
                -75.272485,
                39.876715
              ],
              [
                -75.271463,
                39.877411
              ],
              [
                -75.269685,
                39.879155
              ],
              [
                -75.267702,
                39.879715
              ],
              [
                -75.267477,
                39.880247
              ],
              [
                -75.267015,
                39.880399
              ],
              [
                -75.264433,
                39.882167
              ],
              [
                -75.264928,
                39.881112
              ],
              [
                -75.263328,
                39.879712
              ],
              [
                -75.263467,
                39.878226
              ]
            ]
          ]
        ],
        "type": "MultiPolygon"
      },
      "industries": {
        "allOther": 0,
        "goodsProducing": 0,
        "tradeTransUtil": 2
      },
      "type": "Feature",
      "workTract": "42045403701"
    },
    {
      "geometry": {
        "coordinates": [
          [
            [
              [
                -75.364455,
                40.151393
              ],
              [
                -75.36347,
                40.15102
              ],
              [
                -75.37697,
                40.137572
              ],
              [
                -75.381592,
                40.135478
              ],
              [
                -75.378326,
                40.132649
              ],
              [
                -75.386204,
                40.132122
              ],
              [
                -75.390321,
                40.131627
              ],
              [
                -75.393192,
                40.128615
              ],
              [
                -75.393402,
                40.128019
              ],
              [
                -75.393107,
                40.126855
              ],
              [
                -75.393418,
                40.124159
              ],
              [
                -75.393351,
                40.123491
              ],
              [
                -75.392592,
                40.120775
              ],
              [
                -75.391885,
                40.119899
              ],
              [
                -75.391823,
                40.119614
              ],
              [
                -75.391281,
                40.119587
              ],
              [
                -75.390929,
                40.117807
              ],
              [
                -75.393529,
                40.117204
              ],
              [
                -75.404018,
                40.112865
              ],
              [
                -75.406036,
                40.111771
              ],
              [
                -75.416546,
                40.107859
              ],
              [
                -75.420448,
                40.10735
              ],
              [
                -75.424332,
                40.107906
              ],
              [
                -75.423925,
                40.10831
              ],
              [
                -75.424652,
                40.108531
              ],
              [
                -75.422141,
                40.110749
              ],
              [
                -75.397121,
                40.135054
              ],
              [
                -75.376116,
                40.155871
              ],
              [
                -75.364455,
                40.151393
              ]
            ]
          ]
        ],
        "type": "MultiPolygon"
      },
      "industries": {
        "allOther": 0,
        "goodsProducing": 0,
        "tradeTransUtil": 1
      },
      "type": "Feature",
      "workTract": "42091203402"
    },
    {
      "geometry": {
        "coordinates": [
          [
            [
              [
                -75.163329,
                39.95333
              ],
              [
                -75.165063,
                39.953608
              ],
              [
                -75.165244,
                39.952
              ],
              [
                -75.165055,
                39.95181
              ],
              [
                -75.163917,
                39.951564
              ],
              [
                -75.164011,
                39.950876
              ],
              [
                -75.173489,
                39.952052
              ],
              [
                -75.172783,
                39.955604
              ],
              [
                -75.163093,
                39.9544
              ],
              [
                -75.163329,
                39.95333
              ]
            ]
          ]
        ],
        "type": "MultiPolygon"
      },
      "industries": {
        "allOther": 1,
        "goodsProducing": 0,
        "tradeTransUtil": 0
      },
      "type": "Feature",
      "workTract": "42101000402"
    },
    {
      "geometry": {
        "coordinates": [
          [
            [
              [
                -75.173489,
                39.952052
              ],
              [
                -75.167195,
                39.951263
              ],
              [
                -75.164011,
                39.950876
              ],
              [
                -75.164338,
                39.949346
              ],
              [
                -75.181663,
                39.951509
              ],
              [
                -75.180909,
                39.952982
              ],
              [
                -75.173489,
                39.952052
              ]
            ]
          ]
        ],
        "type": "MultiPolygon"
      },
      "industries": {
        "allOther": 0,
        "goodsProducing": 0,
        "tradeTransUtil": 1
      },
      "type": "Feature",
      "workTract": "42101000700"
    },
    {
      "geometry": {
        "coordinates": [
          [
            [
              [
                -75.164845,
                39.946999
              ],
              [
                -75.17118,
                39.947784
              ],
              [
                -75.170667,
                39.950131
              ],
              [
                -75.164338,
                39.949346
              ],
              [
                -75.164845,
                39.946999
              ]
            ]
          ]
        ],
        "type": "MultiPolygon"
      },
      "industries": {
        "allOther": 1,
        "goodsProducing": 0,
        "tradeTransUtil": 0
      },
      "type": "Feature",
      "workTract": "42101000804"
    },
    {
      "geometry": {
        "coordinates": [
          [
            [
              [
                -75.165341,
                39.944664
              ],
              [
                -75.165575,
                39.943664
              ],
              [
                -75.175054,
                39.944832
              ],
              [
                -75.174323,
                39.948177
              ],
              [
                -75.164845,
                39.946999
              ],
              [
                -75.165341,
                39.944664
              ]
            ]
          ]
        ],
        "type": "MultiPolygon"
      },
      "industries": {
        "allOther": 1,
        "goodsProducing": 0,
        "tradeTransUtil": 0
      },
      "type": "Feature",
      "workTract": "42101001202"
    },
    {
      "geometry": {
        "coordinates": [
          [
            [
              [
                -75.251288,
                39.904403
              ],
              [
                -75.253492,
                39.905585
              ],
              [
                -75.25248,
                39.906633
              ],
              [
                -75.251759,
                39.906744
              ],
              [
                -75.250319,
                39.907626
              ],
              [
                -75.249929,
                39.909352
              ],
              [
                -75.251107,
                39.909708
              ],
              [
                -75.251498,
                39.910051
              ],
              [
                -75.251268,
                39.910031
              ],
              [
                -75.250194,
                39.911196
              ],
              [
                -75.24898,
                39.911749
              ],
              [
                -75.248377,
                39.912934
              ],
              [
                -75.247116,
                39.913678
              ],
              [
                -75.247117,
                39.914043
              ],
              [
                -75.247592,
                39.914362
              ],
              [
                -75.247715,
                39.914837
              ],
              [
                -75.246752,
                39.916232
              ],
              [
                -75.246974,
                39.916939
              ],
              [
                -75.247187,
                39.917094
              ],
              [
                -75.247357,
                39.917993
              ],
              [
                -75.247341,
                39.918541
              ],
              [
                -75.246856,
                39.918759
              ],
              [
                -75.246923,
                39.918313
              ],
              [
                -75.246787,
                39.917915
              ],
              [
                -75.243226,
                39.913112
              ],
              [
                -75.243367,
                39.913005
              ],
              [
                -75.243217,
                39.91249
              ],
              [
                -75.240576,
                39.904062
              ],
              [
                -75.244985,
                39.903178
              ],
              [
                -75.247308,
                39.902282
              ],
              [
                -75.248199,
                39.90178
              ],
              [
                -75.24975,
                39.900548
              ],
              [
                -75.252349,
                39.897618
              ],
              [
                -75.255093,
                39.898756
              ],
              [
                -75.25561,
                39.899576
              ],
              [
                -75.251288,
                39.904403
              ]
            ]
          ]
        ],
        "type": "MultiPolygon"
      },
      "industries": {
        "allOther": 0,
        "goodsProducing": 0,
        "tradeTransUtil": 1
      },
      "type": "Feature",
      "workTract": "42101005500"
    },
    {
      "geometry": {
        "coordinates": [
          [
            [
              [
                -75.205759,
                39.949832
              ],
              [
                -75.208044,
                39.949748
              ],
              [
                -75.209259,
                39.949541
              ],
              [
                -75.209264,
                39.952522
              ],
              [
                -75.208128,
                39.957915
              ],
              [
                -75.204145,
                39.957422
              ],
              [
                -75.204465,
                39.955904
              ],
              [
                -75.204774,
                39.955943
              ],
              [
                -75.20582,
                39.950953
              ],
              [
                -75.205759,
                39.949832
              ]
            ]
          ]
        ],
        "type": "MultiPolygon"
      },
      "industries": {
        "allOther": 2,
        "goodsProducing": 0,
        "tradeTransUtil": 0
      },
      "type": "Feature",
      "workTract": "42101008702"
    },
    {
      "geometry": {
        "coordinates": [
          [
            [
              [
                -75.193574,
                39.958689
              ],
              [
                -75.194152,
                39.95618
              ],
              [
                -75.201953,
                39.957149
              ],
              [
                -75.201824,
                39.957827
              ],
              [
                -75.202235,
                39.961643
              ],
              [
                -75.194297,
                39.962607
              ],
              [
                -75.193574,
                39.958689
              ]
            ]
          ]
        ],
        "type": "MultiPolygon"
      },
      "industries": {
        "allOther": 2,
        "goodsProducing": 0,
        "tradeTransUtil": 0
      },
      "type": "Feature",
      "workTract": "42101009100"
    },
    {
      "geometry": {
        "coordinates": [
          [
            [
              [
                -75.234027,
                39.994736
              ],
              [
                -75.233713,
                39.992176
              ],
              [
                -75.236255,
                39.990971
              ],
              [
                -75.238361,
                39.990486
              ],
              [
                -75.239838,
                39.989287
              ],
              [
                -75.245478,
                39.986619
              ],
              [
                -75.246416,
                39.988266
              ],
              [
                -75.246187,
                39.989516
              ],
              [
                -75.247008,
                39.989933
              ],
              [
                -75.247948,
                39.991138
              ],
              [
                -75.235298,
                39.99707
              ],
              [
                -75.234136,
                39.995598
              ],
              [
                -75.234027,
                39.994736
              ]
            ]
          ]
        ],
        "type": "MultiPolygon"
      },
      "industries": {
        "allOther": 1,
        "goodsProducing": 0,
        "tradeTransUtil": 0
      },
      "type": "Feature",
      "workTract": "42101011700"
    },
    {
      "geometry": {
        "coordinates": [
          [
            [
              [
                -75.121964,
                40.03373
              ],
              [
                -75.121711,
                40.03347
              ],
              [
                -75.123545,
                40.02531
              ],
              [
                -75.127816,
                40.024683
              ],
              [
                -75.131594,
                40.023893
              ],
              [
                -75.131584,
                40.024069
              ],
              [
                -75.133287,
                40.023784
              ],
              [
                -75.13129,
                40.032818
              ],
              [
                -75.127248,
                40.03234
              ],
              [
                -75.125196,
                40.032305
              ],
              [
                -75.123301,
                40.032894
              ],
              [
                -75.121964,
                40.03373
              ]
            ]
          ]
        ],
        "type": "MultiPolygon"
      },
      "industries": {
        "allOther": 1,
        "goodsProducing": 0,
        "tradeTransUtil": 0
      },
      "type": "Feature",
      "workTract": "42101028600"
    },
    {
      "geometry": {
        "coordinates": [
          [
            [
              [
                -75.595632,
                39.755176
              ],
              [
                -75.582039,
                39.749875
              ],
              [
                -75.583405,
                39.747808
              ],
              [
                -75.582836,
                39.747492
              ],
              [
                -75.579531,
                39.746395
              ],
              [
                -75.581385,
                39.743318
              ],
              [
                -75.584652,
                39.744544
              ],
              [
                -75.586236,
                39.74571
              ],
              [
                -75.587949,
                39.746279
              ],
              [
                -75.589605,
                39.745967
              ],
              [
                -75.591875,
                39.745849
              ],
              [
                -75.594762,
                39.744138
              ],
              [
                -75.597115,
                39.744749
              ],
              [
                -75.59939,
                39.743013
              ],
              [
                -75.600103,
                39.744198
              ],
              [
                -75.600419,
                39.744181
              ],
              [
                -75.600792,
                39.744407
              ],
              [
                -75.601658,
                39.74393
              ],
              [
                -75.602378,
                39.744643
              ],
              [
                -75.603451,
                39.743726
              ],
              [
                -75.603446,
                39.743083
              ],
              [
                -75.604562,
                39.741467
              ],
              [
                -75.604547,
                39.740682
              ],
              [
                -75.604831,
                39.739177
              ],
              [
                -75.604672,
                39.738719
              ],
              [
                -75.614919,
                39.737756
              ],
              [
                -75.621134,
                39.737477
              ],
              [
                -75.619874,
                39.738936
              ],
              [
                -75.61788,
                39.740734
              ],
              [
                -75.617635,
                39.740742
              ],
              [
                -75.614684,
                39.742655
              ],
              [
                -75.610483,
                39.74569
              ],
              [
                -75.610183,
                39.746554
              ],
              [
                -75.610085,
                39.747787
              ],
              [
                -75.6102,
                39.748004
              ],
              [
                -75.609518,
                39.752935
              ],
              [
                -75.609006,
                39.754493
              ],
              [
                -75.607581,
                39.756043
              ],
              [
                -75.604372,
                39.75877
              ],
              [
                -75.595632,
                39.755176
              ]
            ]
          ]
        ],
        "type": "MultiPolygon"
      },
      "industries": {
        "allOther": 1,
        "goodsProducing": 0,
        "tradeTransUtil": 0
      },
      "type": "Feature",
      "workTract": "10003012200"
    },
    {
      "geometry": {
        "coordinates": [
          [
            [
              [
                -75.752653,
                39.66588
              ],
              [
                -75.753025,
                39.670109
              ],
              [
                -75.75345,
                39.672117
              ],
              [
                -75.753672,
                39.683014
              ],
              [
                -75.738335,
                39.684275
              ],
              [
                -75.736474,
                39.6845
              ],
              [
                -75.732959,
                39.685373
              ],
              [
                -75.729153,
                39.677472
              ],
              [
                -75.736245,
                39.675276
              ],
              [
                -75.738417,
                39.671333
              ],
              [
                -75.738878,
                39.669402
              ],
              [
                -75.738688,
                39.667747
              ],
              [
                -75.738296,
                39.666523
              ],
              [
                -75.735994,
                39.661576
              ],
              [
                -75.737929,
                39.661155
              ],
              [
                -75.744111,
                39.658958
              ],
              [
                -75.747134,
                39.658305
              ],
              [
                -75.748396,
                39.658228
              ],
              [
                -75.748649,
                39.657614
              ],
              [
                -75.751308,
                39.655748
              ],
              [
                -75.751659,
                39.659382
              ],
              [
                -75.752079,
                39.661411
              ],
              [
                -75.752653,
                39.66588
              ]
            ]
          ]
        ],
        "type": "MultiPolygon"
      },
      "industries": {
        "allOther": 1,
        "goodsProducing": 0,
        "tradeTransUtil": 0
      },
      "type": "Feature",
      "workTract": "10003014502"
    },
    {
      "geometry": {
        "coordinates": [
          [
            [
              [
                -74.943078,
                39.982613
              ],
              [
                -74.935329,
                39.974883
              ],
              [
                -74.931909,
                39.971824
              ],
              [
                -74.943722,
                39.967847
              ],
              [
                -74.951122,
                39.964822
              ],
              [
                -74.970234,
                39.962778
              ],
              [
                -74.974459,
                39.962208
              ],
              [
                -74.976988,
                39.961674
              ],
              [
                -74.971244,
                39.967441
              ],
              [
                -74.961993,
                39.977665
              ],
              [
                -74.960312,
                39.982931
              ],
              [
                -74.957751,
                39.982407
              ],
              [
                -74.955012,
                39.981302
              ],
              [
                -74.949171,
                39.975732
              ],
              [
                -74.94574,
                39.985272
              ],
              [
                -74.943078,
                39.982613
              ]
            ]
          ]
        ],
        "type": "MultiPolygon"
      },
      "industries": {
        "allOther": 0,
        "goodsProducing": 0,
        "tradeTransUtil": 1
      },
      "type": "Feature",
      "workTract": "34005700503"
    },
    {
      "geometry": {
        "coordinates": [
          [
            [
              [
                -74.893643,
                39.975905
              ],
              [
                -74.889067,
                39.972825
              ],
              [
                -74.888505,
                39.972306
              ],
              [
                -74.880038,
                39.957044
              ],
              [
                -74.868848,
                39.938431
              ],
              [
                -74.862313,
                39.931103
              ],
              [
                -74.862474,
                39.919828
              ],
              [
                -74.867195,
                39.919445
              ],
              [
                -74.879382,
                39.918987
              ],
              [
                -74.878734,
                39.920819
              ],
              [
                -74.892386,
                39.935198
              ],
              [
                -74.930587,
                39.960843
              ],
              [
                -74.925159,
                39.963821
              ],
              [
                -74.909004,
                39.97416
              ],
              [
                -74.905503,
                39.976173
              ],
              [
                -74.898823,
                39.980576
              ],
              [
                -74.893643,
                39.975905
              ]
            ]
          ]
        ],
        "type": "MultiPolygon"
      },
      "industries": {
        "allOther": 0,
        "goodsProducing": 1,
        "tradeTransUtil": 0
      },
      "type": "Feature",
      "workTract": "34005702910"
    },
    {
      "geometry": {
        "coordinates": [
          [
            [
              [
                -74.935034,
                39.902736
              ],
              [
                -74.928421,
                39.894609
              ],
              [
                -74.927511,
                39.893302
              ],
              [
                -74.928975,
                39.893817
              ],
              [
                -74.93999,
                39.895648
              ],
              [
                -74.945191,
                39.895704
              ],
              [
                -74.945317,
                39.896114
              ],
              [
                -74.946809,
                39.897313
              ],
              [
                -74.949427,
                39.898234
              ],
              [
                -74.950609,
                39.899649
              ],
              [
                -74.950657,
                39.899983
              ],
              [
                -74.951357,
                39.900955
              ],
              [
                -74.95179,
                39.901352
              ],
              [
                -74.952148,
                39.903195
              ],
              [
                -74.951967,
                39.904076
              ],
              [
                -74.952465,
                39.905785
              ],
              [
                -74.952303,
                39.906959
              ],
              [
                -74.953888,
                39.908832
              ],
              [
                -74.954889,
                39.911646
              ],
              [
                -74.955804,
                39.913176
              ],
              [
                -74.956705,
                39.913445
              ],
              [
                -74.957223,
                39.91428
              ],
              [
                -74.943523,
                39.91488
              ],
              [
                -74.939837,
                39.908685
              ],
              [
                -74.935034,
                39.902736
              ]
            ]
          ]
        ],
        "type": "MultiPolygon"
      },
      "industries": {
        "allOther": 1,
        "goodsProducing": 0,
        "tradeTransUtil": 0
      },
      "type": "Feature",
      "workTract": "34005704005"
    },
    {
      "geometry": {
        "coordinates": [
          [
            [
              [
                -74.862736,
                39.896622
              ],
              [
                -74.862731,
                39.890787
              ],
              [
                -74.862533,
                39.888698
              ],
              [
                -74.862628,
                39.879425
              ],
              [
                -74.862457,
                39.876764
              ],
              [
                -74.862814,
                39.873115
              ],
              [
                -74.86273,
                39.855744
              ],
              [
                -74.874756,
                39.859979
              ],
              [
                -74.894643,
                39.867297
              ],
              [
                -74.896005,
                39.87584
              ],
              [
                -74.886189,
                39.876416
              ],
              [
                -74.885634,
                39.87678
              ],
              [
                -74.886423,
                39.885057
              ],
              [
                -74.883557,
                39.887969
              ],
              [
                -74.883298,
                39.88841
              ],
              [
                -74.884413,
                39.894128
              ],
              [
                -74.880704,
                39.89443
              ],
              [
                -74.862673,
                39.89736
              ],
              [
                -74.862736,
                39.896622
              ]
            ]
          ]
        ],
        "type": "MultiPolygon"
      },
      "industries": {
        "allOther": 1,
        "goodsProducing": 0,
        "tradeTransUtil": 0
      },
      "type": "Feature",
      "workTract": "34005704009"
    },
    {
      "geometry": {
        "coordinates": [
          [
            [
              [
                -74.738923,
                40.12493
              ],
              [
                -74.741318,
                40.127143
              ],
              [
                -74.745613,
                40.125254
              ],
              [
                -74.747611,
                40.123466
              ],
              [
                -74.748887,
                40.122554
              ],
              [
                -74.750226,
                40.122097
              ],
              [
                -74.753969,
                40.121537
              ],
              [
                -74.756754,
                40.121353
              ],
              [
                -74.761196,
                40.121358
              ],
              [
                -74.766728,
                40.123912
              ],
              [
                -74.773029,
                40.124373
              ],
              [
                -74.776027,
                40.125004
              ],
              [
                -74.76909,
                40.129187
              ],
              [
                -74.763764,
                40.132136
              ],
              [
                -74.762323,
                40.132881
              ],
              [
                -74.758745,
                40.13413
              ],
              [
                -74.756006,
                40.134778
              ],
              [
                -74.75313,
                40.135033
              ],
              [
                -74.749565,
                40.134888
              ],
              [
                -74.745097,
                40.134394
              ],
              [
                -74.7432,
                40.134538
              ],
              [
                -74.741184,
                40.135165
              ],
              [
                -74.736565,
                40.138258
              ],
              [
                -74.73174,
                40.141929
              ],
              [
                -74.730863,
                40.142169
              ],
              [
                -74.727486,
                40.144253
              ],
              [
                -74.726122,
                40.145444
              ],
              [
                -74.724369,
                40.146412
              ],
              [
                -74.724174,
                40.147322
              ],
              [
                -74.723184,
                40.147065
              ],
              [
                -74.721619,
                40.147044
              ],
              [
                -74.719468,
                40.147701
              ],
              [
                -74.718635,
                40.147306
              ],
              [
                -74.716965,
                40.146151
              ],
              [
                -74.715685,
                40.14629
              ],
              [
                -74.715002,
                40.144859
              ],
              [
                -74.715035,
                40.14419
              ],
              [
                -74.715494,
                40.143732
              ],
              [
                -74.716518,
                40.143194
              ],
              [
                -74.716535,
                40.142067
              ],
              [
                -74.716154,
                40.140953
              ],
              [
                -74.716224,
                40.140491
              ],
              [
                -74.715852,
                40.140456
              ],
              [
                -74.71508,
                40.141226
              ],
              [
                -74.714509,
                40.141255
              ],
              [
                -74.714342,
                40.140952
              ],
              [
                -74.71448,
                40.139676
              ],
              [
                -74.713199,
                40.139397
              ],
              [
                -74.712422,
                40.138335
              ],
              [
                -74.711659,
                40.138295
              ],
              [
                -74.710688,
                40.138979
              ],
              [
                -74.707347,
                40.140396
              ],
              [
                -74.701111,
                40.14471
              ],
              [
                -74.70037,
                40.145557
              ],
              [
                -74.70043,
                40.149478
              ],
              [
                -74.700607,
                40.149474
              ],
              [
                -74.700433,
                40.150257
              ],
              [
                -74.698574,
                40.15063
              ],
              [
                -74.682429,
                40.152839
              ],
              [
                -74.681981,
                40.147887
              ],
              [
                -74.681289,
                40.143619
              ],
              [
                -74.682133,
                40.141847
              ],
              [
                -74.681966,
                40.138702
              ],
              [
                -74.68186,
                40.137954
              ],
              [
                -74.680982,
                40.137278
              ],
              [
                -74.681238,
                40.131493
              ],
              [
                -74.68055,
                40.130313
              ],
              [
                -74.679973,
                40.125493
              ],
              [
                -74.682533,
                40.124883
              ],
              [
                -74.690061,
                40.124394
              ],
              [
                -74.690948,
                40.124194
              ],
              [
                -74.6922,
                40.123454
              ],
              [
                -74.694566,
                40.122483
              ],
              [
                -74.695162,
                40.121953
              ],
              [
                -74.696072,
                40.12055
              ],
              [
                -74.699745,
                40.117244
              ],
              [
                -74.700533,
                40.116701
              ],
              [
                -74.701861,
                40.116222
              ],
              [
                -74.703321,
                40.115982
              ],
              [
                -74.705209,
                40.116384
              ],
              [
                -74.7066,
                40.116469
              ],
              [
                -74.709641,
                40.115701
              ],
              [
                -74.710676,
                40.115303
              ],
              [
                -74.711253,
                40.114704
              ],
              [
                -74.72104,
                40.113846
              ],
              [
                -74.722874,
                40.113188
              ],
              [
                -74.723915,
                40.115493
              ],
              [
                -74.724438,
                40.115701
              ],
              [
                -74.72524,
                40.116379
              ],
              [
                -74.727236,
                40.116294
              ],
              [
                -74.727386,
                40.11669
              ],
              [
                -74.728446,
                40.117206
              ],
              [
                -74.730263,
                40.119355
              ],
              [
                -74.73226,
                40.1209
              ],
              [
                -74.733603,
                40.121475
              ],
              [
                -74.734438,
                40.122306
              ],
              [
                -74.73557,
                40.122731
              ],
              [
                -74.736954,
                40.123011
              ],
              [
                -74.738923,
                40.12493
              ]
            ]
          ]
        ],
        "type": "MultiPolygon"
      },
      "industries": {
        "allOther": 0,
        "goodsProducing": 1,
        "tradeTransUtil": 0
      },
      "type": "Feature",
      "workTract": "34005704200"
    },
    {
      "geometry": {
        "coordinates": [
          [
            [
              [
                -74.995944,
                39.940068
              ],
              [
                -74.995072,
                39.939852
              ],
              [
                -74.99474,
                39.939366
              ],
              [
                -74.994442,
                39.939266
              ],
              [
                -74.993954,
                39.939411
              ],
              [
                -74.993285,
                39.940015
              ],
              [
                -74.992407,
                39.940068
              ],
              [
                -74.991754,
                39.940879
              ],
              [
                -74.990256,
                39.94087
              ],
              [
                -74.989118,
                39.941059
              ],
              [
                -74.988799,
                39.94096
              ],
              [
                -74.988633,
                39.940708
              ],
              [
                -74.987487,
                39.940591
              ],
              [
                -74.987272,
                39.940094
              ],
              [
                -74.986802,
                39.939897
              ],
              [
                -74.985364,
                39.940095
              ],
              [
                -74.984549,
                39.939867
              ],
              [
                -74.98331,
                39.940383
              ],
              [
                -74.979145,
                39.940319
              ],
              [
                -74.976395,
                39.939814
              ],
              [
                -74.975644,
                39.939264
              ],
              [
                -74.974879,
                39.938382
              ],
              [
                -74.975945,
                39.936781
              ],
              [
                -74.976509,
                39.935535
              ],
              [
                -74.978128,
                39.934913
              ],
              [
                -74.978596,
                39.934282
              ],
              [
                -74.980979,
                39.934121
              ],
              [
                -74.981501,
                39.933456
              ],
              [
                -74.981481,
                39.933157
              ],
              [
                -74.980786,
                39.931992
              ],
              [
                -74.980991,
                39.931241
              ],
              [
                -74.988933,
                39.933456
              ],
              [
                -74.997965,
                39.925177
              ],
              [
                -75.013542,
                39.928334
              ],
              [
                -75.01225,
                39.930183
              ],
              [
                -75.012039,
                39.930747
              ],
              [
                -75.010015,
                39.939594
              ],
              [
                -75.009948,
                39.940152
              ],
              [
                -75.010276,
                39.940197
              ],
              [
                -75.010421,
                39.940508
              ],
              [
                -75.010244,
                39.940772
              ],
              [
                -75.009709,
                39.940952
              ],
              [
                -75.00921,
                39.94515
              ],
              [
                -75.008661,
                39.944501
              ],
              [
                -75.007283,
                39.944087
              ],
              [
                -75.006851,
                39.943105
              ],
              [
                -75.005699,
                39.942358
              ],
              [
                -75.004936,
                39.942105
              ],
              [
                -75.004264,
                39.941555
              ],
              [
                -75.003116,
                39.941519
              ],
              [
                -75.000629,
                39.941834
              ],
              [
                -75.000243,
                39.941663
              ],
              [
                -75.000067,
                39.941224
              ],
              [
                -74.998862,
                39.940723
              ],
              [
                -74.998702,
                39.94024
              ],
              [
                -74.99784,
                39.940204
              ],
              [
                -74.996484,
                39.940519
              ],
              [
                -74.995944,
                39.940068
              ]
            ]
          ]
        ],
        "type": "MultiPolygon"
      },
      "industries": {
        "allOther": 0,
        "goodsProducing": 0,
        "tradeTransUtil": 1
      },
      "type": "Feature",
      "workTract": "34007603302"
    },
    {
      "geometry": {
        "coordinates": [
          [
            [
              [
                -74.945714,
                39.895732
              ],
              [
                -74.948353,
                39.896257
              ],
              [
                -74.966763,
                39.902786
              ],
              [
                -74.968607,
                39.888618
              ],
              [
                -74.969998,
                39.882121
              ],
              [
                -74.975369,
                39.885254
              ],
              [
                -74.997219,
                39.88959
              ],
              [
                -74.972795,
                39.914527
              ],
              [
                -74.969722,
                39.917366
              ],
              [
                -74.965775,
                39.920615
              ],
              [
                -74.964146,
                39.920683
              ],
              [
                -74.9628,
                39.920102
              ],
              [
                -74.962341,
                39.919466
              ],
              [
                -74.961413,
                39.918853
              ],
              [
                -74.960683,
                39.91733
              ],
              [
                -74.959039,
                39.916529
              ],
              [
                -74.958618,
                39.916176
              ],
              [
                -74.956705,
                39.913445
              ],
              [
                -74.955804,
                39.913176
              ],
              [
                -74.954889,
                39.911646
              ],
              [
                -74.953888,
                39.908832
              ],
              [
                -74.952303,
                39.906959
              ],
              [
                -74.952465,
                39.905785
              ],
              [
                -74.951967,
                39.904076
              ],
              [
                -74.952148,
                39.903195
              ],
              [
                -74.95179,
                39.901352
              ],
              [
                -74.951357,
                39.900955
              ],
              [
                -74.950657,
                39.899983
              ],
              [
                -74.950609,
                39.899649
              ],
              [
                -74.949637,
                39.898423
              ],
              [
                -74.949166,
                39.898107
              ],
              [
                -74.946809,
                39.897313
              ],
              [
                -74.945317,
                39.896114
              ],
              [
                -74.945191,
                39.895704
              ],
              [
                -74.945714,
                39.895732
              ]
            ]
          ]
        ],
        "type": "MultiPolygon"
      },
      "industries": {
        "allOther": 1,
        "goodsProducing": 0,
        "tradeTransUtil": 0
      },
      "type": "Feature",
      "workTract": "34007603501"
    },
    {
      "geometry": {
        "coordinates": [
          [
            [
              [
                -74.980842,
                39.82846
              ],
              [
                -74.981102,
                39.828818
              ],
              [
                -74.981405,
                39.828638
              ],
              [
                -74.982632,
                39.829813
              ],
              [
                -74.983774,
                39.831164
              ],
              [
                -74.984273,
                39.832211
              ],
              [
                -74.985855,
                39.834095
              ],
              [
                -74.984684,
                39.835819
              ],
              [
                -74.98196,
                39.8357
              ],
              [
                -74.981924,
                39.836446
              ],
              [
                -74.981049,
                39.837752
              ],
              [
                -74.98095,
                39.838247
              ],
              [
                -74.979761,
                39.839733
              ],
              [
                -74.979425,
                39.840427
              ],
              [
                -74.978701,
                39.840993
              ],
              [
                -74.977611,
                39.84147
              ],
              [
                -74.977184,
                39.841867
              ],
              [
                -74.975218,
                39.842993
              ],
              [
                -74.972048,
                39.844262
              ],
              [
                -74.971007,
                39.844478
              ],
              [
                -74.970607,
                39.844834
              ],
              [
                -74.970471,
                39.844568
              ],
              [
                -74.96961,
                39.844154
              ],
              [
                -74.965914,
                39.845585
              ],
              [
                -74.964652,
                39.845701
              ],
              [
                -74.964374,
                39.845332
              ],
              [
                -74.963026,
                39.845046
              ],
              [
                -74.962496,
                39.844545
              ],
              [
                -74.959299,
                39.842721
              ],
              [
                -74.956136,
                39.840565
              ],
              [
                -74.953199,
                39.839421
              ],
              [
                -74.951101,
                39.838915
              ],
              [
                -74.951132,
                39.838542
              ],
              [
                -74.949611,
                39.836682
              ],
              [
                -74.949549,
                39.834913
              ],
              [
                -74.949113,
                39.832806
              ],
              [
                -74.948272,
                39.831793
              ],
              [
                -74.948092,
                39.830439
              ],
              [
                -74.950174,
                39.828639
              ],
              [
                -74.953498,
                39.827102
              ],
              [
                -74.950665,
                39.822429
              ],
              [
                -74.958616,
                39.822409
              ],
              [
                -74.957964,
                39.817611
              ],
              [
                -74.963237,
                39.820914
              ],
              [
                -74.965672,
                39.821267
              ],
              [
                -74.966532,
                39.82183
              ],
              [
                -74.966469,
                39.822173
              ],
              [
                -74.966819,
                39.822279
              ],
              [
                -74.967986,
                39.824052
              ],
              [
                -74.97032,
                39.826309
              ],
              [
                -74.97141,
                39.826012
              ],
              [
                -74.973092,
                39.826709
              ],
              [
                -74.973477,
                39.8272
              ],
              [
                -74.974671,
                39.826961
              ],
              [
                -74.975478,
                39.826138
              ],
              [
                -74.97579,
                39.826158
              ],
              [
                -74.978792,
                39.826829
              ],
              [
                -74.978661,
                39.827057
              ],
              [
                -74.979103,
                39.827085
              ],
              [
                -74.980341,
                39.827655
              ],
              [
                -74.980634,
                39.828369
              ],
              [
                -74.980842,
                39.82846
              ]
            ]
          ]
        ],
        "type": "MultiPolygon"
      },
      "industries": {
        "allOther": 1,
        "goodsProducing": 0,
        "tradeTransUtil": 0
      },
      "type": "Feature",
      "workTract": "34007607600"
    },
    {
      "geometry": {
        "coordinates": [
          [
            [
              [
                -75.217086,
                39.83078
              ],
              [
                -75.198629,
                39.838032
              ],
              [
                -75.19505,
                39.839551
              ],
              [
                -75.190402,
                39.841822
              ],
              [
                -75.163446,
                39.832886
              ],
              [
                -75.16399,
                39.830187
              ],
              [
                -75.16214,
                39.828081
              ],
              [
                -75.16131,
                39.824663
              ],
              [
                -75.174277,
                39.819131
              ],
              [
                -75.186716,
                39.81476
              ],
              [
                -75.20277,
                39.809983
              ],
              [
                -75.202964,
                39.810449
              ],
              [
                -75.202601,
                39.811305
              ],
              [
                -75.203096,
                39.812359
              ],
              [
                -75.204446,
                39.814279
              ],
              [
                -75.20639,
                39.815475
              ],
              [
                -75.208509,
                39.815216
              ],
              [
                -75.208854,
                39.815345
              ],
              [
                -75.209111,
                39.81467
              ],
              [
                -75.208532,
                39.814069
              ],
              [
                -75.208531,
                39.813788
              ],
              [
                -75.208719,
                39.813549
              ],
              [
                -75.210004,
                39.81292
              ],
              [
                -75.210347,
                39.812546
              ],
              [
                -75.211208,
                39.812208
              ],
              [
                -75.211928,
                39.812468
              ],
              [
                -75.213942,
                39.813796
              ],
              [
                -75.214624,
                39.813588
              ],
              [
                -75.215949,
                39.813552
              ],
              [
                -75.217667,
                39.812945
              ],
              [
                -75.220821,
                39.815217
              ],
              [
                -75.219934,
                39.816273
              ],
              [
                -75.21962,
                39.816885
              ],
              [
                -75.219657,
                39.817121
              ],
              [
                -75.220972,
                39.818617
              ],
              [
                -75.221435,
                39.819922
              ],
              [
                -75.224305,
                39.821558
              ],
              [
                -75.224965,
                39.822675
              ],
              [
                -75.226081,
                39.823035
              ],
              [
                -75.226419,
                39.823705
              ],
              [
                -75.226224,
                39.824505
              ],
              [
                -75.226516,
                39.825083
              ],
              [
                -75.227113,
                39.825754
              ],
              [
                -75.22766,
                39.826065
              ],
              [
                -75.223046,
                39.828338
              ],
              [
                -75.217086,
                39.83078
              ]
            ]
          ]
        ],
        "type": "MultiPolygon"
      },
      "industries": {
        "allOther": 0,
        "goodsProducing": 0,
        "tradeTransUtil": 1
      },
      "type": "Feature",
      "workTract": "34015500204"
    }
  ],
  "modesOfTransport": {},
  "type": "FeatureCollection"
}
